{
    "lang": "ja_JP",
    "eventid": "act28side",
    "eventName": "ダーティマネー",
    "entryType": "ACTIVITY",
    "storyCode": "CV-1",
    "avgTag": "戦闘前",
    "storyName": "孤独の地",
    "storyInfo": "野獣に襲われかけたジェシカは現地の老狩人に助けられた。そして共に深い林を抜け、任務地であるデイヴィスタウンまで案内してもらうことになった。一方、小隊メンバーはジェシカの身を案じつつ区画へと向かう。\n",
    "storyList": [
        {
            "id": 0,
            "prop": "HEADER",
            "attributes": {
                "key": "title_test",
                "is_skippable": "true",
                "fit_mode": "BLACK_MASK"
            }
        },
        {
            "id": 1,
            "prop": "stopmusic",
            "attributes": {}
        },
        {
            "id": 2,
            "prop": "dialog",
            "attributes": {}
        },
        {
            "id": 3,
            "prop": "warp",
            "attributes": {
                "name": "chiyu01"
            }
        },
        {
            "id": 4,
            "prop": "Blocker",
            "attributes": {
                "a": 0.0,
                "r": 0.0,
                "g": 0.0,
                "b": 0.0,
                "fadetime": 0.0,
                "block": "true"
            }
        },
        {
            "id": 5,
            "prop": "Blocker",
            "attributes": {
                "a": 1.0,
                "r": 0.0,
                "g": 0.0,
                "b": 0.0,
                "fadetime": 2.0,
                "block": "true"
            }
        },
        {
            "id": 6,
            "prop": "charslot",
            "attributes": {}
        },
        {
            "id": 7,
            "prop": "Background",
            "attributes": {
                "image": "bg_iceforest_2",
                "screenadapt": "coverall"
            }
        },
        {
            "id": 8,
            "prop": "PlaySound",
            "attributes": {
                "key": "$d_avg_snowstormflp",
                "volume": 1.0,
                "loop": "true",
                "channel": "a"
            }
        },
        {
            "id": 9,
            "prop": "charslot",
            "attributes": {
                "slot": "m",
                "name": "avg_1034_jesca2_1#3$1"
            }
        },
        {
            "id": 10,
            "prop": "Blocker",
            "attributes": {
                "a": 0.0,
                "r": 0.0,
                "g": 0.0,
                "b": 0.0,
                "fadetime": 2.0,
                "block": "true"
            }
        },
        {
            "id": 11,
            "prop": "Delay",
            "attributes": {
                "time": 1.0
            }
        },
        {
            "id": 12,
            "prop": "charslot",
            "attributes": {
                "slot": "m",
                "name": "avg_1034_jesca2_1#3$1",
                "focus": "n"
            }
        },
        {
            "id": 13,
            "prop": "name",
            "attributes": {
                "content": "ジェシカは慌てながらも、瞬時に腰の銃へと手を伸ばした。しかし恐怖のせいか彼女はホルスターに指を掛けたまま、曲げることができなかった。"
            }
        },
        {
            "id": 14,
            "prop": "name",
            "attributes": {
                "content": "冷たい風の中、かすかな血の匂いがした。"
            }
        },
        {
            "id": 15,
            "prop": "dialog",
            "attributes": {}
        },
        {
            "id": 16,
            "prop": "charslot",
            "attributes": {
                "slot": "m",
                "name": "avg_1034_jesca2_1#11$1"
            }
        },
        {
            "id": 17,
            "prop": "delay",
            "attributes": {
                "time": 1.0
            }
        },
        {
            "id": 18,
            "prop": "charslot",
            "attributes": {
                "slot": "m",
                "name": "avg_1034_jesca2_1#11$1",
                "focus": "n"
            }
        },
        {
            "id": 19,
            "prop": "name",
            "attributes": {
                "content": "動くな。",
                "name": "？？？"
            }
        },
        {
            "id": 20,
            "prop": "dialog",
            "attributes": {}
        },
        {
            "id": 21,
            "prop": "charslot",
            "attributes": {}
        },
        {
            "id": 22,
            "prop": "StopSound",
            "attributes": {
                "channel": "a",
                "fadetime": 1.0
            }
        },
        {
            "id": 23,
            "prop": "CameraShake",
            "attributes": {
                "duration": 0.3,
                "xstrength": 30.0,
                "ystrength": 30.0,
                "vibrato": 30.0,
                "randomness": 90.0,
                "fadeout": "true",
                "block": "false"
            }
        },
        {
            "id": 24,
            "prop": "Blocker",
            "attributes": {
                "a": 0.0,
                "r": 0.0,
                "g": 0.0,
                "b": 0.0,
                "fadetime": 0.0,
                "block": "true"
            }
        },
        {
            "id": 25,
            "prop": "PlaySound",
            "attributes": {
                "key": "$d_avg_gunshot",
                "volume": 1.0
            }
        },
        {
            "id": 26,
            "prop": "Blocker",
            "attributes": {
                "a": 1.0,
                "r": 0.0,
                "g": 0.0,
                "b": 0.0,
                "fadetime": 0.1,
                "block": "true"
            }
        },
        {
            "id": 27,
            "prop": "Blocker",
            "attributes": {
                "a": 0.0,
                "r": 0.0,
                "g": 0.0,
                "b": 0.0,
                "fadetime": 0.5,
                "block": "true"
            }
        },
        {
            "id": 28,
            "prop": "delay",
            "attributes": {
                "time": 0.5
            }
        },
        {
            "id": 29,
            "prop": "PlaySound",
            "attributes": {
                "key": "$d_avg_fmalebstwhin",
                "volume": 0.6
            }
        },
        {
            "id": 30,
            "prop": "delay",
            "attributes": {
                "time": 1.0
            }
        },
        {
            "id": 31,
            "prop": "PlaySound",
            "attributes": {
                "key": "$bodyfalldown2",
                "volume": 1.0
            }
        },
        {
            "id": 32,
            "prop": "delay",
            "attributes": {
                "time": 2.0
            }
        },
        {
            "id": 33,
            "prop": "PlaySound",
            "attributes": {
                "key": "$d_avg_snowstormflp",
                "volume": 1.0,
                "loop": "true",
                "channel": "a"
            }
        },
        {
            "id": 34,
            "prop": "SoundVolume",
            "attributes": {
                "volume": 1.0,
                "channel": "a",
                "fadetime": 3.0
            }
        },
        {
            "id": 35,
            "prop": "PlaySound",
            "attributes": {
                "key": "$d_avg_wind",
                "volume": 1.0
            }
        },
        {
            "id": 36,
            "prop": "Blocker",
            "attributes": {
                "a": 0.0,
                "r": 255.0,
                "g": 255.0,
                "b": 255.0,
                "fadetime": 0.0,
                "block": "true"
            }
        },
        {
            "id": 37,
            "prop": "Blocker",
            "attributes": {
                "a": 0.3,
                "r": 255.0,
                "g": 255.0,
                "b": 255.0,
                "fadetime": 0.8,
                "block": "true"
            }
        },
        {
            "id": 38,
            "prop": "Blocker",
            "attributes": {
                "a": 0.0,
                "r": 255.0,
                "g": 255.0,
                "b": 255.0,
                "fadetime": 1.5,
                "block": "true"
            }
        },
        {
            "id": 39,
            "prop": "Blocker",
            "attributes": {
                "a": 0.5,
                "r": 255.0,
                "g": 255.0,
                "b": 255.0,
                "fadetime": 2.0
            }
        },
        {
            "id": 40,
            "prop": "PlaySound",
            "attributes": {
                "key": "$d_avg_snowbootwalk",
                "volume": 1.0
            }
        },
        {
            "id": 41,
            "prop": "delay",
            "attributes": {
                "time": 1.0
            }
        },
        {
            "id": 42,
            "prop": "PlayMusic",
            "attributes": {
                "intro": "$loading_intro",
                "key": "$loading_loop",
                "volume": 0.6
            }
        },
        {
            "id": 43,
            "prop": "charslot",
            "attributes": {
                "slot": "m",
                "name": "avg_npc_1034_1#1$1",
                "bstart": 0.2,
                "bend": 0.7,
                "duration": 2.0,
                "isblock": "true"
            }
        },
        {
            "id": 44,
            "prop": "name",
            "attributes": {
                "content": "林から出てきた一人の狩人が、ジェシカの視界へと進み出た。帽子の広いつばが彼の目元を覆い隠し、その手にある銃の銃口からは煙がまだ立ち上っている。"
            }
        },
        {
            "id": 45,
            "prop": "dialog",
            "attributes": {}
        },
        {
            "id": 46,
            "prop": "charslot",
            "attributes": {}
        },
        {
            "id": 47,
            "prop": "delay",
            "attributes": {
                "time": 1.0
            }
        },
        {
            "id": 48,
            "prop": "name",
            "attributes": {
                "content": "振り返って背後を見ると、野獣の死体が雪の上に横たわっており、その頭部の傷口からは鮮血がどくどくと流れ出ていた。"
            }
        },
        {
            "id": 49,
            "prop": "dialog",
            "attributes": {}
        },
        {
            "id": 50,
            "prop": "Blocker",
            "attributes": {
                "a": 0.0,
                "r": 255.0,
                "g": 255.0,
                "b": 255.0,
                "fadetime": 2.0
            }
        },
        {
            "id": 51,
            "prop": "charslot",
            "attributes": {
                "slot": "m",
                "name": "avg_npc_1034_1#1$1",
                "duration": 2.0,
                "isblock": "true"
            }
        },
        {
            "id": 52,
            "prop": "StopSound",
            "attributes": {
                "channel": "a",
                "fadetime": 2.0
            }
        },
        {
            "id": 53,
            "prop": "name",
            "attributes": {
                "content": "ここじゃもっと用心することだな。",
                "name": "年老いた狩人"
            },
            "figure_art": "avg_npc_1034_1#1$1"
        },
        {
            "id": 54,
            "prop": "charslot",
            "attributes": {
                "slot": "m",
                "name": "avg_1034_jesca2_1#15$1"
            }
        },
        {
            "id": 55,
            "prop": "name",
            "attributes": {
                "content": "……助けていただき……ありがとうございます。",
                "name": "ジェシカ"
            },
            "figure_art": "avg_1034_jesca2_1#15$1"
        },
        {
            "id": 56,
            "prop": "charslot",
            "attributes": {
                "slot": "m",
                "name": "avg_npc_1034_1#10$1"
            }
        },
        {
            "id": 57,
            "prop": "name",
            "attributes": {
                "content": "事のついでだ。",
                "name": "年老いた狩人"
            },
            "figure_art": "avg_npc_1034_1#10$1"
        },
        {
            "id": 58,
            "prop": "dialog",
            "attributes": {}
        },
        {
            "id": 59,
            "prop": "PlaySound",
            "attributes": {
                "key": "$d_avg_snowbootwalk",
                "volume": 1.0
            }
        },
        {
            "id": 60,
            "prop": "charslot",
            "attributes": {
                "duration": 1.5,
                "isblock": "true"
            }
        },
        {
            "id": 61,
            "prop": "name",
            "attributes": {
                "content": "老人は銃をしまいながら、野獣の死体へとまっすぐ向かう。"
            }
        },
        {
            "id": 62,
            "prop": "dialog",
            "attributes": {}
        },
        {
            "id": 63,
            "prop": "PlaySound",
            "attributes": {
                "key": "$d_avg_knife",
                "volume": 1.0
            }
        },
        {
            "id": 64,
            "prop": "delay",
            "attributes": {
                "time": 1.0
            }
        },
        {
            "id": 65,
            "prop": "name",
            "attributes": {
                "content": "彼はナイフを取り出すと、正確な角度で野獣の腹部を切り裂いた。そのため余計な血がこぼれることはなかった。"
            }
        },
        {
            "id": 66,
            "prop": "name",
            "attributes": {
                "content": "そして、彼は両手を死体の腹の中へ突っ込むと、長いためいきをついた。"
            }
        },
        {
            "id": 67,
            "prop": "charslot",
            "attributes": {
                "slot": "r",
                "name": "avg_1034_jesca2_1#1$1",
                "focus": "n"
            }
        },
        {
            "id": 68,
            "prop": "charslot",
            "attributes": {
                "slot": "l",
                "name": "avg_npc_1034_1#2$1",
                "focus": "l"
            }
        },
        {
            "id": 69,
            "prop": "name",
            "attributes": {
                "content": "しっかしクソみてぇに寒いな。",
                "name": "年老いた狩人"
            },
            "figure_art": "avg_npc_1034_1#2$1"
        },
        {
            "id": 70,
            "prop": "charslot",
            "attributes": {
                "slot": "r",
                "name": "avg_1034_jesca2_1#1$1",
                "focus": "r"
            }
        },
        {
            "id": 71,
            "prop": "name",
            "attributes": {
                "content": "……お爺さんは、この近くに住む狩人さんですか？",
                "name": "ジェシカ"
            },
            "figure_art": "avg_1034_jesca2_1#1$1"
        },
        {
            "id": 72,
            "prop": "charslot",
            "attributes": {
                "slot": "l",
                "name": "avg_npc_1034_1#1$1",
                "focus": "l"
            }
        },
        {
            "id": 73,
            "prop": "name",
            "attributes": {
                "content": "まあそんなところだ。",
                "name": "年老いた狩人"
            },
            "figure_art": "avg_npc_1034_1#1$1"
        },
        {
            "id": 74,
            "prop": "charslot",
            "attributes": {
                "slot": "r",
                "name": "avg_1034_jesca2_1#16$1",
                "focus": "r"
            }
        },
        {
            "id": 75,
            "prop": "name",
            "attributes": {
                "content": "でしたら、デイヴィスタウンへの道はご存知ですか？",
                "name": "ジェシカ"
            },
            "figure_art": "avg_1034_jesca2_1#16$1"
        },
        {
            "id": 76,
            "prop": "charslot",
            "attributes": {
                "slot": "l",
                "name": "avg_npc_1034_1#10$1",
                "focus": "l"
            }
        },
        {
            "id": 77,
            "prop": "name",
            "attributes": {
                "content": "……あそこに何の用だ？",
                "name": "年老いた狩人"
            },
            "figure_art": "avg_npc_1034_1#10$1"
        },
        {
            "id": 78,
            "prop": "charslot",
            "attributes": {
                "slot": "r",
                "name": "avg_1034_jesca2_1#16$1",
                "focus": "r"
            }
        },
        {
            "id": 79,
            "prop": "name",
            "attributes": {
                "content": "そこで仲間と合流しようと思っています。",
                "name": "ジェシカ"
            },
            "figure_art": "avg_1034_jesca2_1#16$1"
        },
        {
            "id": 80,
            "prop": "charslot",
            "attributes": {
                "slot": "l",
                "name": "avg_npc_1034_1#10$1",
                "focus": "l"
            }
        },
        {
            "id": 81,
            "prop": "name",
            "attributes": {
                "content": "一人で来たんじゃないのか。",
                "name": "年老いた狩人"
            },
            "figure_art": "avg_npc_1034_1#10$1"
        },
        {
            "id": 82,
            "prop": "charslot",
            "attributes": {
                "slot": "r",
                "name": "avg_1034_jesca2_1#14$1",
                "focus": "r"
            }
        },
        {
            "id": 83,
            "prop": "name",
            "attributes": {
                "content": "はい。野盗からの人質救出任務にあたっていました。仲間とは別行動を取っていて、任務終了後にわたしの通信機が壊れ、林の中で迷子になってしまって……",
                "name": "ジェシカ"
            },
            "figure_art": "avg_1034_jesca2_1#14$1"
        },
        {
            "id": 84,
            "prop": "charslot",
            "attributes": {
                "slot": "l",
                "name": "avg_npc_1034_1#10$1",
                "focus": "l"
            }
        },
        {
            "id": 85,
            "prop": "name",
            "attributes": {
                "content": "人質？　そいつはどんなやつだ？",
                "name": "年老いた狩人"
            },
            "figure_art": "avg_npc_1034_1#10$1"
        },
        {
            "id": 86,
            "prop": "charslot",
            "attributes": {
                "slot": "r",
                "name": "avg_1034_jesca2_1#14$1",
                "focus": "r"
            }
        },
        {
            "id": 87,
            "prop": "name",
            "attributes": {
                "content": "ご年配のフォルテの男性ですが……",
                "name": "ジェシカ"
            },
            "figure_art": "avg_1034_jesca2_1#14$1"
        },
        {
            "id": 88,
            "prop": "charslot",
            "attributes": {
                "slot": "l",
                "name": "avg_npc_1034_1#4$1",
                "focus": "l"
            }
        },
        {
            "id": 89,
            "prop": "name",
            "attributes": {
                "content": "……そうか、お前たちが。",
                "name": "年老いた狩人"
            },
            "figure_art": "avg_npc_1034_1#4$1"
        },
        {
            "id": 90,
            "prop": "charslot",
            "attributes": {
                "slot": "l",
                "name": "avg_npc_1034_1#1$1",
                "focus": "l"
            }
        },
        {
            "id": 91,
            "prop": "name",
            "attributes": {
                "content": "なら、ついて来い。",
                "name": "年老いた狩人"
            },
            "figure_art": "avg_npc_1034_1#1$1"
        },
        {
            "id": 92,
            "prop": "charslot",
            "attributes": {
                "slot": "r",
                "name": "avg_1034_jesca2_1#3$1",
                "focus": "r"
            }
        },
        {
            "id": 93,
            "prop": "name",
            "attributes": {
                "content": "ど、どちらへ行かれるんですか？",
                "name": "ジェシカ"
            },
            "figure_art": "avg_1034_jesca2_1#3$1"
        },
        {
            "id": 94,
            "prop": "charslot",
            "attributes": {
                "slot": "l",
                "name": "avg_npc_1034_1#1$1",
                "focus": "l"
            }
        },
        {
            "id": 95,
            "prop": "name",
            "attributes": {
                "content": "デイヴィスタウンに行きたいんじゃなかったのか？",
                "name": "年老いた狩人"
            },
            "figure_art": "avg_npc_1034_1#1$1"
        },
        {
            "id": 96,
            "prop": "charslot",
            "attributes": {
                "slot": "r",
                "name": "avg_1034_jesca2_1#1$1",
                "focus": "r"
            }
        },
        {
            "id": 97,
            "prop": "name",
            "attributes": {
                "content": "それはそうですが……",
                "name": "ジェシカ"
            },
            "figure_art": "avg_1034_jesca2_1#1$1"
        },
        {
            "id": 98,
            "prop": "charslot",
            "attributes": {
                "slot": "l",
                "name": "avg_npc_1034_1#5$1",
                "focus": "l"
            }
        },
        {
            "id": 99,
            "prop": "name",
            "attributes": {
                "content": "ま、来るか来ないかはお前の自由だ。",
                "name": "年老いた狩人"
            },
            "figure_art": "avg_npc_1034_1#5$1"
        },
        {
            "id": 100,
            "prop": "dialog",
            "attributes": {}
        },
        {
            "id": 101,
            "prop": "PlaySound",
            "attributes": {
                "key": "$d_avg_cloakmovement",
                "volume": 1.0
            }
        },
        {
            "id": 102,
            "prop": "charslot",
            "attributes": {
                "slot": "l",
                "posfrom": "0,0",
                "posto": "0,-20",
                "duration": 1.0,
                "isblock": "true"
            }
        },
        {
            "id": 103,
            "prop": "delay",
            "attributes": {
                "time": 0.5
            }
        },
        {
            "id": 104,
            "prop": "charslot",
            "attributes": {
                "slot": "l",
                "posfrom": "0,-20",
                "posto": "0,0",
                "duration": 0.3,
                "isblock": "true"
            }
        },
        {
            "id": 105,
            "prop": "delay",
            "attributes": {
                "time": 0.5
            }
        },
        {
            "id": 106,
            "prop": "PlaySound",
            "attributes": {
                "key": "$d_avg_snowbootwalk",
                "volume": 1.0
            }
        },
        {
            "id": 107,
            "prop": "charslot",
            "attributes": {
                "slot": "l",
                "posfrom": "0,0",
                "posto": "-300,0",
                "afrom": 1.0,
                "ato": 0.0,
                "duration": 2.0,
                "isblock": "true"
            }
        },
        {
            "id": 108,
            "prop": "charslot",
            "attributes": {
                "slot": "r",
                "name": "avg_1034_jesca2_1#1$1",
                "focus": "n"
            }
        },
        {
            "id": 109,
            "prop": "name",
            "attributes": {
                "content": "そう言うや否や老人はジェシカには目もくれず、野獣の死体を肩に担いで立ち上がり、足早に林の奥へと去っていった。"
            }
        },
        {
            "id": 110,
            "prop": "charslot",
            "attributes": {
                "slot": "r",
                "name": "avg_1034_jesca2_1#3$1",
                "focus": "r"
            }
        },
        {
            "id": 111,
            "prop": "name",
            "attributes": {
                "content": "ま、待ってください！",
                "name": "ジェシカ"
            },
            "figure_art": "avg_1034_jesca2_1#3$1"
        },
        {
            "id": 112,
            "prop": "dialog",
            "attributes": {}
        },
        {
            "id": 113,
            "prop": "PlaySound",
            "attributes": {
                "key": "$d_avg_snowrun",
                "volume": 1.0,
                "loop": "true",
                "channel": "d"
            }
        },
        {
            "id": 114,
            "prop": "StopSound",
            "attributes": {
                "channel": "d",
                "fadetime": 2.0
            }
        },
        {
            "id": 115,
            "prop": "charslot",
            "attributes": {
                "slot": "r",
                "posfrom": "0,0",
                "posto": "-500,0",
                "afrom": 1.0,
                "ato": 0.0,
                "duration": 1.0,
                "isblock": "true"
            }
        },
        {
            "id": 116,
            "prop": "musicvolume",
            "attributes": {
                "volume": 0.2,
                "fadetime": 2.0
            }
        },
        {
            "id": 117,
            "prop": "Blocker",
            "attributes": {
                "a": 0.0,
                "r": 0.0,
                "g": 0.0,
                "b": 0.0,
                "fadetime": 0.0,
                "block": "true"
            }
        },
        {
            "id": 118,
            "prop": "Blocker",
            "attributes": {
                "a": 1.0,
                "r": 0.0,
                "g": 0.0,
                "b": 0.0,
                "fadetime": 2.0,
                "block": "true"
            }
        },
        {
            "id": 119,
            "prop": "charslot",
            "attributes": {}
        },
        {
            "id": 120,
            "prop": "Background",
            "attributes": {
                "image": "bg_iceforest_2",
                "screenadapt": "coverall"
            }
        },
        {
            "id": 121,
            "prop": "Delay",
            "attributes": {
                "time": 1.0
            }
        },
        {
            "id": 122,
            "prop": "musicvolume",
            "attributes": {
                "volume": 0.6,
                "fadetime": 2.0
            }
        },
        {
            "id": 123,
            "prop": "Blocker",
            "attributes": {
                "a": 0.0,
                "r": 0.0,
                "g": 0.0,
                "b": 0.0,
                "fadetime": 2.0,
                "block": "true"
            }
        },
        {
            "id": 124,
            "prop": "Delay",
            "attributes": {
                "time": 1.0
            }
        },
        {
            "id": 125,
            "prop": "charslot",
            "attributes": {
                "slot": "l",
                "name": "avg_106_franka_1#1$1",
                "focus": "l"
            }
        },
        {
            "id": 126,
            "prop": "charslot",
            "attributes": {
                "slot": "r",
                "name": "avg_107_liskam_1#1$1",
                "focus": "n"
            }
        },
        {
            "id": 127,
            "prop": "name",
            "attributes": {
                "content": "はぁ、こんなところでジェシカを一人にして、ほんとに大丈夫？",
                "name": "フランカ"
            }
        },
        {
            "id": 128,
            "prop": "charslot",
            "attributes": {
                "slot": "r",
                "name": "avg_107_liskam_1#1$1",
                "focus": "r"
            }
        },
        {
            "id": 129,
            "prop": "name",
            "attributes": {
                "content": "心配なのはわたしだって同じだよ。でもここ数年一緒に戦ってきてわかるんでしょ、彼女なら自力で対処できるって。",
                "name": "リスカム"
            },
            "figure_art": "avg_107_liskam_1#1$1"
        },
        {
            "id": 130,
            "prop": "charslot",
            "attributes": {
                "slot": "l",
                "name": "avg_106_franka_1#4$1",
                "focus": "l"
            }
        },
        {
            "id": 131,
            "prop": "name",
            "attributes": {
                "content": "あたしはただ野盗の残りがいないか気になってるだけ。二人三人なら問題ないけど、別で動いてる連中がいたら？",
                "name": "フランカ"
            },
            "figure_art": "avg_106_franka_1#4$1"
        },
        {
            "id": 132,
            "prop": "charslot",
            "attributes": {
                "slot": "r",
                "name": "avg_107_liskam_1#1$1",
                "focus": "r"
            }
        },
        {
            "id": 133,
            "prop": "name",
            "attributes": {
                "content": "ジェシカがこれまでに経験した戦いは、あんな烏合の衆の相手よりもはるかに危険なものだったよね。",
                "name": "リスカム"
            },
            "figure_art": "avg_107_liskam_1#1$1"
        },
        {
            "id": 134,
            "prop": "charslot",
            "attributes": {
                "slot": "l",
                "name": "avg_106_franka_1#4$1",
                "focus": "l"
            }
        },
        {
            "id": 135,
            "prop": "name",
            "attributes": {
                "content": "……",
                "name": "フランカ"
            },
            "figure_art": "avg_106_franka_1#4$1"
        },
        {
            "id": 136,
            "prop": "charslot",
            "attributes": {
                "slot": "r",
                "name": "avg_107_liskam_1#2$1",
                "focus": "r"
            }
        },
        {
            "id": 137,
            "prop": "name",
            "attributes": {
                "content": "矢がすぐ頭上を通り過ぎたり、鋭い刃が喉元をかすめたり。",
                "name": "リスカム"
            },
            "figure_art": "avg_107_liskam_1#2$1"
        },
        {
            "id": 138,
            "prop": "name",
            "attributes": {
                "content": "高濃度の活性源石粉塵に囲まれた環境に置かれたこともあった。防護服に少しでも穴が開いたらそこでゲームオーバーってレベルの、ね。",
                "name": "リスカム"
            },
            "figure_art": "avg_107_liskam_1#2$1"
        },
        {
            "id": 139,
            "prop": "charslot",
            "attributes": {
                "slot": "r",
                "name": "avg_107_liskam_1#1$1",
                "focus": "r"
            }
        },
        {
            "id": 140,
            "prop": "name",
            "attributes": {
                "content": "それでも彼女は毎回見事に任務を達成してきた。わたしたちの同行なしでも、わたしたちが見ていなくとも。",
                "name": "リスカム"
            },
            "figure_art": "avg_107_liskam_1#1$1"
        },
        {
            "id": 141,
            "prop": "charslot",
            "attributes": {
                "slot": "r",
                "name": "avg_107_liskam_1#9$1",
                "focus": "r"
            }
        },
        {
            "id": 142,
            "prop": "name",
            "attributes": {
                "content": "たった一人で、何でも上手くこなしてきたでしょ。",
                "name": "リスカム"
            },
            "figure_art": "avg_107_liskam_1#9$1"
        },
        {
            "id": 143,
            "prop": "charslot",
            "attributes": {
                "slot": "l",
                "name": "avg_106_franka_1#4$1",
                "focus": "l"
            }
        },
        {
            "id": 144,
            "prop": "name",
            "attributes": {
                "content": "……それについては否定しないけど。",
                "name": "フランカ"
            },
            "figure_art": "avg_106_franka_1#4$1"
        },
        {
            "id": 145,
            "prop": "charslot",
            "attributes": {
                "slot": "l",
                "name": "avg_106_franka_1#10$1",
                "focus": "l"
            }
        },
        {
            "id": 146,
            "prop": "name",
            "attributes": {
                "content": "でも、そのたびに目の周りを真っ赤にして帰ってくるのも事実じゃない。あたしたちに会う前にわんわん泣きじゃくってるんなら、その時誰かしらそばに居てあげなきゃって思わない？",
                "name": "フランカ"
            },
            "figure_art": "avg_106_franka_1#10$1"
        },
        {
            "id": 147,
            "prop": "charslot",
            "attributes": {
                "slot": "r",
                "name": "avg_107_liskam_1#1$1",
                "focus": "r"
            }
        },
        {
            "id": 148,
            "prop": "name",
            "attributes": {
                "content": "ジェシカが毎回目を真っ赤にしてる理由までは考えないの？　いつも涙を拭いてから会いに来てるからだよ。つまり、彼女は泣いてるところを誰にも見られたくないんだって。",
                "name": "リスカム"
            },
            "figure_art": "avg_107_liskam_1#1$1"
        },
        {
            "id": 149,
            "prop": "charslot",
            "attributes": {
                "slot": "l",
                "name": "avg_106_franka_1#5$1",
                "focus": "l"
            }
        },
        {
            "id": 150,
            "prop": "name",
            "attributes": {
                "content": "だけどあの子はまだ二十三歳よ――",
                "name": "フランカ"
            },
            "figure_art": "avg_106_franka_1#5$1"
        },
        {
            "id": 151,
            "prop": "charslot",
            "attributes": {
                "slot": "r",
                "name": "avg_107_liskam_1#3$1",
                "focus": "r"
            }
        },
        {
            "id": 152,
            "prop": "name",
            "attributes": {
                "content": "そうだね、まだ二十三歳。しかもこの三年のうち、二年半も戦場で過ごしてきた……",
                "name": "リスカム"
            },
            "figure_art": "avg_107_liskam_1#3$1"
        },
        {
            "id": 153,
            "prop": "dialog",
            "attributes": {}
        },
        {
            "id": 154,
            "prop": "musicvolume",
            "attributes": {
                "volume": 0.2,
                "fadetime": 2.0
            }
        },
        {
            "id": 155,
            "prop": "Blocker",
            "attributes": {
                "a": 0.0,
                "r": 0.0,
                "g": 0.0,
                "b": 0.0,
                "fadetime": 0.0,
                "block": "true"
            }
        },
        {
            "id": 156,
            "prop": "Blocker",
            "attributes": {
                "a": 1.0,
                "r": 0.0,
                "g": 0.0,
                "b": 0.0,
                "fadetime": 2.0,
                "block": "true"
            }
        },
        {
            "id": 157,
            "prop": "musicvolume",
            "attributes": {
                "volume": 0.6,
                "fadetime": 2.0
            }
        },
        {
            "id": 158,
            "prop": "charslot",
            "attributes": {}
        },
        {
            "id": 159,
            "prop": "Background",
            "attributes": {
                "image": "bg_iceforest_2",
                "screenadapt": "coverall"
            }
        },
        {
            "id": 160,
            "prop": "Delay",
            "attributes": {
                "time": 1.0
            }
        },
        {
            "id": 161,
            "prop": "Blocker",
            "attributes": {
                "a": 0.0,
                "r": 0.0,
                "g": 0.0,
                "b": 0.0,
                "fadetime": 2.0,
                "block": "true"
            }
        },
        {
            "id": 162,
            "prop": "Delay",
            "attributes": {
                "time": 1.0
            }
        },
        {
            "id": 163,
            "prop": "PlaySound",
            "attributes": {
                "key": "$d_avg_treefrzrupture",
                "volume": 0.2
            }
        },
        {
            "id": 164,
            "prop": "Delay",
            "attributes": {
                "time": 1.0
            }
        },
        {
            "id": 165,
            "prop": "PlaySound",
            "attributes": {
                "key": "$d_avg_snowbootwalk",
                "volume": 1.0
            }
        },
        {
            "id": 166,
            "prop": "charslot",
            "attributes": {
                "slot": "l",
                "name": "avg_npc_1034_1#1$1",
                "posfrom": "300,0",
                "posto": "0,0",
                "duration": 2.0
            }
        },
        {
            "id": 167,
            "prop": "Delay",
            "attributes": {
                "time": 1.0
            }
        },
        {
            "id": 168,
            "prop": "PlaySound",
            "attributes": {
                "key": "$d_avg_snowbootwalk",
                "volume": 0.4
            }
        },
        {
            "id": 169,
            "prop": "charslot",
            "attributes": {
                "slot": "r",
                "name": "avg_1034_jesca2_1#1$1",
                "posfrom": "200,0",
                "posto": "0,0",
                "duration": 1.5,
                "isblock": "true"
            }
        },
        {
            "id": 170,
            "prop": "Delay",
            "attributes": {
                "time": 1.0
            }
        },
        {
            "id": 171,
            "prop": "charslot",
            "attributes": {
                "slot": "l",
                "name": "avg_npc_1034_1#1$1",
                "focus": "n"
            }
        },
        {
            "id": 172,
            "prop": "charslot",
            "attributes": {
                "slot": "r",
                "name": "avg_1034_jesca2_1#16$1",
                "focus": "r"
            }
        },
        {
            "id": 173,
            "prop": "name",
            "attributes": {
                "content": "お爺さん、近くで何か爆発しませんでしたか？",
                "name": "ジェシカ"
            },
            "figure_art": "avg_1034_jesca2_1#16$1"
        },
        {
            "id": 174,
            "prop": "charslot",
            "attributes": {
                "slot": "l",
                "name": "avg_npc_1034_1#1$1",
                "focus": "l"
            }
        },
        {
            "id": 175,
            "prop": "name",
            "attributes": {
                "content": "いや。",
                "name": "年老いた狩人"
            },
            "figure_art": "avg_npc_1034_1#1$1"
        },
        {
            "id": 176,
            "prop": "dialog",
            "attributes": {}
        },
        {
            "id": 177,
            "prop": "charslot",
            "attributes": {
                "slot": "l",
                "name": "avg_npc_1034_1#1$1",
                "focus": "n"
            }
        },
        {
            "id": 178,
            "prop": "PlaySound",
            "attributes": {
                "key": "$d_avg_treefrzrupture",
                "volume": 0.6
            }
        },
        {
            "id": 179,
            "prop": "Delay",
            "attributes": {
                "time": 1.0
            }
        },
        {
            "id": 180,
            "prop": "PlaySound",
            "attributes": {
                "key": "$d_avg_snowfall",
                "volume": 0.6
            }
        },
        {
            "id": 181,
            "prop": "Delay",
            "attributes": {
                "time": 2.5
            }
        },
        {
            "id": 182,
            "prop": "charslot",
            "attributes": {
                "slot": "r",
                "name": "avg_1034_jesca2_1#3$1",
                "focus": "r"
            }
        },
        {
            "id": 183,
            "prop": "name",
            "attributes": {
                "content": "また聞こえた気が、このすぐ近くです……わたしの幻聴でしょうか……",
                "name": "ジェシカ"
            },
            "figure_art": "avg_1034_jesca2_1#3$1"
        },
        {
            "id": 184,
            "prop": "charslot",
            "attributes": {
                "slot": "l",
                "name": "avg_npc_1034_1#1$1",
                "focus": "l"
            }
        },
        {
            "id": 185,
            "prop": "name",
            "attributes": {
                "content": "ありゃ爆発じゃない、木だ。",
                "name": "年老いた狩人"
            },
            "figure_art": "avg_npc_1034_1#1$1"
        },
        {
            "id": 186,
            "prop": "charslot",
            "attributes": {
                "slot": "r",
                "name": "avg_1034_jesca2_1#16$1",
                "focus": "r"
            }
        },
        {
            "id": 187,
            "prop": "name",
            "attributes": {
                "content": "木？",
                "name": "ジェシカ"
            },
            "figure_art": "avg_1034_jesca2_1#16$1"
        },
        {
            "id": 188,
            "prop": "charslot",
            "attributes": {
                "slot": "l",
                "name": "avg_npc_1034_1#1$1",
                "focus": "l"
            }
        },
        {
            "id": 189,
            "prop": "name",
            "attributes": {
                "content": "寒すぎるせいでな。樹液が凍って膨張し、木の幹の組織を破裂させてああいう音を立てるんだよ。",
                "name": "年老いた狩人"
            },
            "figure_art": "avg_npc_1034_1#1$1"
        },
        {
            "id": 190,
            "prop": "charslot",
            "attributes": {
                "slot": "r",
                "name": "avg_1034_jesca2_1#1$1",
                "focus": "r"
            }
        },
        {
            "id": 191,
            "prop": "name",
            "attributes": {
                "content": "なんだか……遠くで戦っている音のように聞こえます。",
                "name": "ジェシカ"
            },
            "figure_art": "avg_1034_jesca2_1#1$1"
        },
        {
            "id": 192,
            "prop": "charslot",
            "attributes": {
                "slot": "l",
                "name": "avg_npc_1034_1#10$1",
                "focus": "l"
            }
        },
        {
            "id": 193,
            "prop": "name",
            "attributes": {
                "content": "お前は一体何者だ？　軍の者か？　傭兵か？",
                "name": "年老いた狩人"
            },
            "figure_art": "avg_npc_1034_1#10$1"
        },
        {
            "id": 194,
            "prop": "charslot",
            "attributes": {
                "slot": "r",
                "name": "avg_1034_jesca2_1#1$1",
                "focus": "r"
            }
        },
        {
            "id": 195,
            "prop": "name",
            "attributes": {
                "content": "傭兵です、もう五年ほどやっています。",
                "name": "ジェシカ"
            },
            "figure_art": "avg_1034_jesca2_1#1$1"
        },
        {
            "id": 196,
            "prop": "charslot",
            "attributes": {
                "slot": "l",
                "name": "avg_npc_1034_1#10$1",
                "focus": "l"
            }
        },
        {
            "id": 197,
            "prop": "name",
            "attributes": {
                "content": "家が借金でも抱えてるのか？",
                "name": "年老いた狩人"
            },
            "figure_art": "avg_npc_1034_1#10$1"
        },
        {
            "id": 198,
            "prop": "charslot",
            "attributes": {
                "slot": "r",
                "name": "avg_1034_jesca2_1#10$1",
                "focus": "r"
            }
        },
        {
            "id": 199,
            "prop": "name",
            "attributes": {
                "content": "いえ……わたしはただ……家族に守られて、敷かれたレールの上を歩きたくなかったので……",
                "name": "ジェシカ"
            },
            "figure_art": "avg_1034_jesca2_1#10$1"
        },
        {
            "id": 200,
            "prop": "charslot",
            "attributes": {
                "slot": "l",
                "name": "avg_npc_1034_1#1$1",
                "focus": "l"
            }
        },
        {
            "id": 201,
            "prop": "name",
            "attributes": {
                "content": "それで傭兵なんかになったのか？",
                "name": "年老いた狩人"
            },
            "figure_art": "avg_npc_1034_1#1$1"
        },
        {
            "id": 202,
            "prop": "charslot",
            "attributes": {
                "slot": "r",
                "name": "avg_1034_jesca2_1#10$1",
                "focus": "r"
            }
        },
        {
            "id": 203,
            "prop": "name",
            "attributes": {
                "content": "は、はい……",
                "name": "ジェシカ"
            },
            "figure_art": "avg_1034_jesca2_1#10$1"
        },
        {
            "id": 204,
            "prop": "charslot",
            "attributes": {
                "slot": "l",
                "name": "avg_npc_1034_1#1$1",
                "focus": "l"
            }
        },
        {
            "id": 205,
            "prop": "name",
            "attributes": {
                "content": "フッ、ならお前は戦場に何を求めてる？　富か、名声か、それとも栄誉か？",
                "name": "年老いた狩人"
            },
            "figure_art": "avg_npc_1034_1#1$1"
        },
        {
            "id": 206,
            "prop": "charslot",
            "attributes": {
                "slot": "r",
                "name": "avg_1034_jesca2_1#11$1",
                "focus": "r"
            }
        },
        {
            "id": 207,
            "prop": "name",
            "attributes": {
                "content": "いえ、わたしがやりたいのは危険の排除や、衝突の解決、それに窮地から人々を守ることです……",
                "name": "ジェシカ"
            },
            "figure_art": "avg_1034_jesca2_1#11$1"
        },
        {
            "id": 208,
            "prop": "charslot",
            "attributes": {
                "slot": "l",
                "name": "avg_npc_1034_1#8$1",
                "focus": "l"
            }
        },
        {
            "id": 209,
            "prop": "name",
            "attributes": {
                "content": "ほう……傭兵ってのはそういうことをするようなもんだったか？　初めて知ったな。",
                "name": "年老いた狩人"
            },
            "figure_art": "avg_npc_1034_1#8$1"
        },
        {
            "id": 210,
            "prop": "dialog",
            "attributes": {}
        },
        {
            "id": 211,
            "prop": "charslot",
            "attributes": {}
        },
        {
            "id": 212,
            "prop": "PlaySound",
            "attributes": {
                "key": "$d_avg_treefrzrupture",
                "volume": 1.0
            }
        },
        {
            "id": 213,
            "prop": "Delay",
            "attributes": {
                "time": 1.0
            }
        },
        {
            "id": 214,
            "prop": "PlaySound",
            "attributes": {
                "key": "$d_avg_snowfall",
                "volume": 1.0
            }
        },
        {
            "id": 215,
            "prop": "Delay",
            "attributes": {
                "time": 1.0
            }
        },
        {
            "id": 216,
            "prop": "charslot",
            "attributes": {
                "slot": "m",
                "name": "avg_1034_jesca2_1#3$1"
            }
        },
        {
            "id": 217,
            "prop": "name",
            "attributes": {
                "content": "お爺さん……わたしたちはただの傭兵企業ではなくて、わたしたちは……",
                "name": "ジェシカ"
            },
            "figure_art": "avg_1034_jesca2_1#3$1"
        },
        {
            "id": 218,
            "prop": "dialog",
            "attributes": {}
        },
        {
            "id": 219,
            "prop": "PlaySound",
            "attributes": {
                "key": "$flashback",
                "volume": 0.8
            }
        },
        {
            "id": 220,
            "prop": "Blocker",
            "attributes": {
                "a": 0.0,
                "r": 255.0,
                "g": 255.0,
                "b": 255.0,
                "fadetime": 0.0,
                "block": "true"
            }
        },
        {
            "id": 221,
            "prop": "Blocker",
            "attributes": {
                "a": 1.0,
                "r": 255.0,
                "g": 255.0,
                "b": 255.0,
                "fadetime": 0.5,
                "block": "true"
            }
        },
        {
            "id": 222,
            "prop": "charslot",
            "attributes": {}
        },
        {
            "id": 223,
            "prop": "Background",
            "attributes": {
                "image": "42_g9_modernoffice",
                "screenadapt": "coverall"
            }
        },
        {
            "id": 224,
            "prop": "charslot",
            "attributes": {
                "slot": "m",
                "name": "avg_npc_1036_1#1$1"
            }
        },
        {
            "id": 225,
            "prop": "CameraEffect",
            "attributes": {
                "effect": "Grayscale",
                "amount": 0.8,
                "keep": "true"
            }
        },
        {
            "id": 226,
            "prop": "Blocker",
            "attributes": {
                "a": 0.0,
                "r": 0.0,
                "g": 0.0,
                "b": 0.0,
                "fadetime": 0.5,
                "block": "true"
            }
        },
        {
            "id": 227,
            "prop": "Delay",
            "attributes": {
                "time": 1.0
            }
        },
        {
            "id": 228,
            "prop": "name",
            "attributes": {
                "content": "一つ忠告しておく、ジェシカ。お前は傭兵だ。行っている任務はビジネスであり、ボランティアではない。",
                "name": "「クリップ」クリフ"
            },
            "figure_art": "avg_npc_1036_1#1$1"
        },
        {
            "id": 229,
            "prop": "dialog",
            "attributes": {}
        },
        {
            "id": 230,
            "prop": "PlaySound",
            "attributes": {
                "key": "$flashback",
                "volume": 0.8
            }
        },
        {
            "id": 231,
            "prop": "Blocker",
            "attributes": {
                "a": 0.0,
                "r": 255.0,
                "g": 255.0,
                "b": 255.0,
                "fadetime": 0.0,
                "block": "true"
            }
        },
        {
            "id": 232,
            "prop": "Blocker",
            "attributes": {
                "a": 1.0,
                "r": 255.0,
                "g": 255.0,
                "b": 255.0,
                "fadetime": 0.5,
                "block": "true"
            }
        },
        {
            "id": 233,
            "prop": "charslot",
            "attributes": {}
        },
        {
            "id": 234,
            "prop": "Background",
            "attributes": {
                "image": "bg_iceforest_2",
                "screenadapt": "coverall"
            }
        },
        {
            "id": 235,
            "prop": "charslot",
            "attributes": {
                "slot": "m",
                "name": "avg_1034_jesca2_1#1$1"
            }
        },
        {
            "id": 236,
            "prop": "CameraEffect",
            "attributes": {
                "effect": "Grayscale",
                "amount": 0.0,
                "keep": "true"
            }
        },
        {
            "id": 237,
            "prop": "Blocker",
            "attributes": {
                "a": 0.0,
                "r": 0.0,
                "g": 0.0,
                "b": 0.0,
                "fadetime": 0.5,
                "block": "true"
            }
        },
        {
            "id": 238,
            "prop": "Delay",
            "attributes": {
                "time": 1.0
            }
        },
        {
            "id": 239,
            "prop": "name",
            "attributes": {
                "content": "わたしたちは……",
                "name": "ジェシカ"
            },
            "figure_art": "avg_1034_jesca2_1#1$1"
        },
        {
            "id": 240,
            "prop": "charslot",
            "attributes": {
                "slot": "m",
                "name": "avg_npc_1034_1#10$1"
            }
        },
        {
            "id": 241,
            "prop": "name",
            "attributes": {
                "content": "もういい。俺はそんな御託には興味がない。",
                "name": "年老いた狩人"
            },
            "figure_art": "avg_npc_1034_1#10$1"
        },
        {
            "id": 242,
            "prop": "dialog",
            "attributes": {}
        },
        {
            "id": 243,
            "prop": "PlaySound",
            "attributes": {
                "key": "$d_avg_snowbootwalk",
                "volume": 1.0
            }
        },
        {
            "id": 244,
            "prop": "charslot",
            "attributes": {
                "slot": "m",
                "posfrom": "0,0",
                "posto": "-300,0",
                "afrom": 1.0,
                "ato": 0.0,
                "duration": 1.5,
                "isblock": "true"
            }
        },
        {
            "id": 245,
            "prop": "charslot",
            "attributes": {}
        },
        {
            "id": 246,
            "prop": "charslot",
            "attributes": {
                "slot": "m",
                "name": "avg_1034_jesca2_1#3$1"
            }
        },
        {
            "id": 247,
            "prop": "Delay",
            "attributes": {
                "time": 0.5
            }
        },
        {
            "id": 248,
            "prop": "charslot",
            "attributes": {
                "slot": "m",
                "name": "avg_1034_jesca2_1#11$1"
            }
        },
        {
            "id": 249,
            "prop": "Delay",
            "attributes": {
                "time": 0.5
            }
        },
        {
            "id": 250,
            "prop": "PlaySound",
            "attributes": {
                "key": "$d_avg_snowrun",
                "volume": 1.0,
                "loop": "true",
                "channel": "d"
            }
        },
        {
            "id": 251,
            "prop": "StopSound",
            "attributes": {
                "channel": "d",
                "fadetime": 2.0
            }
        },
        {
            "id": 252,
            "prop": "charslot",
            "attributes": {
                "slot": "m",
                "posfrom": "0,0",
                "posto": "-300,0",
                "afrom": 1.0,
                "ato": 0.0,
                "duration": 1.0,
                "isblock": "true"
            }
        },
        {
            "id": 253,
            "prop": "musicvolume",
            "attributes": {
                "volume": 0.2,
                "fadetime": 2.0
            }
        },
        {
            "id": 254,
            "prop": "Blocker",
            "attributes": {
                "a": 0.0,
                "r": 0.0,
                "g": 0.0,
                "b": 0.0,
                "fadetime": 0.0,
                "block": "true"
            }
        },
        {
            "id": 255,
            "prop": "Blocker",
            "attributes": {
                "a": 1.0,
                "r": 0.0,
                "g": 0.0,
                "b": 0.0,
                "fadetime": 2.0,
                "block": "true"
            }
        },
        {
            "id": 256,
            "prop": "musicvolume",
            "attributes": {
                "volume": 0.6,
                "fadetime": 2.0
            }
        },
        {
            "id": 257,
            "prop": "charslot",
            "attributes": {}
        },
        {
            "id": 258,
            "prop": "Delay",
            "attributes": {
                "time": 1.0
            }
        },
        {
            "id": 259,
            "prop": "Blocker",
            "attributes": {
                "a": 0.0,
                "r": 0.0,
                "g": 0.0,
                "b": 0.0,
                "fadetime": 2.0,
                "block": "true"
            }
        },
        {
            "id": 260,
            "prop": "Delay",
            "attributes": {
                "time": 1.0
            }
        },
        {
            "id": 261,
            "prop": "PlaySound",
            "attributes": {
                "key": "$d_avg_snowbootwalk",
                "volume": 1.0
            }
        },
        {
            "id": 262,
            "prop": "delay",
            "attributes": {
                "time": 1.0
            }
        },
        {
            "id": 263,
            "prop": "charslot",
            "attributes": {
                "slot": "m",
                "name": "avg_4105_almond_1#1$1",
                "duration": 2.0,
                "isblock": "true"
            }
        },
        {
            "id": 264,
            "prop": "name",
            "attributes": {
                "content": "ちょっといいかな？　二人とも。今話してたのは五年の実戦経験を持つ「ベテラン」傭兵のことだよね？",
                "name": "ローラ"
            },
            "figure_art": "avg_4105_almond_1#1$1"
        },
        {
            "id": 265,
            "prop": "charslot",
            "attributes": {
                "slot": "m",
                "name": "avg_106_franka_1#3$1"
            }
        },
        {
            "id": 266,
            "prop": "name",
            "attributes": {
                "content": "あら、何か言いたいことでもあるのかしら、ローラちゃん。",
                "name": "フランカ"
            },
            "figure_art": "avg_106_franka_1#3$1"
        },
        {
            "id": 267,
            "prop": "charslot",
            "attributes": {
                "slot": "m",
                "name": "avg_4105_almond_1#1$1"
            }
        },
        {
            "id": 268,
            "prop": "name",
            "attributes": {
                "content": "ジェシカちゃんと一緒に仕事してきた時間はキミたちの方が長い。彼女の能力も限界も、キミたちの方があたしちゃんよりもよく知ってるはずでしょ？",
                "name": "ローラ"
            },
            "figure_art": "avg_4105_almond_1#1$1"
        },
        {
            "id": 269,
            "prop": "charslot",
            "attributes": {
                "slot": "m",
                "name": "avg_106_franka_1#1$1"
            }
        },
        {
            "id": 270,
            "prop": "name",
            "attributes": {
                "content": "つまり、ジェシカなら自力で解決できるって言いたいのね？",
                "name": "フランカ"
            },
            "figure_art": "avg_106_franka_1#1$1"
        },
        {
            "id": 271,
            "prop": "charslot",
            "attributes": {
                "slot": "m",
                "name": "avg_4105_almond_1#11$1"
            }
        },
        {
            "id": 272,
            "prop": "name",
            "attributes": {
                "content": "もちろん。だってリスカム隊長の言う通り、この三年、あの子はここよりもずっと危険な場所で任務にあたってきたんだし。",
                "name": "ローラ"
            },
            "figure_art": "avg_4105_almond_1#11$1"
        },
        {
            "id": 273,
            "prop": "charslot",
            "attributes": {
                "slot": "m",
                "name": "avg_4105_almond_1#1$1"
            }
        },
        {
            "id": 274,
            "prop": "name",
            "attributes": {
                "content": "目をうるうるさせてるジェシカちゃんの姿を思い浮かべると、あたしちゃんも思わず心配になっちゃうけど、本当は大丈夫だってことくらいみんなわかってる。そうでしょ？",
                "name": "ローラ"
            },
            "figure_art": "avg_4105_almond_1#1$1"
        },
        {
            "id": 275,
            "prop": "charslot",
            "attributes": {
                "slot": "m",
                "name": "avg_107_liskam_1#2$1"
            }
        },
        {
            "id": 276,
            "prop": "name",
            "attributes": {
                "content": "彼女自身を除いてみんな、ね。",
                "name": "リスカム"
            },
            "figure_art": "avg_107_liskam_1#2$1"
        },
        {
            "id": 277,
            "prop": "charslot",
            "attributes": {
                "slot": "m",
                "name": "avg_4105_almond_1#3$1"
            }
        },
        {
            "id": 278,
            "prop": "name",
            "attributes": {
                "content": "そ、わかってないのはジェシカちゃんだけなんだよねぇ……",
                "name": "ローラ"
            },
            "figure_art": "avg_4105_almond_1#3$1"
        },
        {
            "id": 279,
            "prop": "charslot",
            "attributes": {
                "slot": "m",
                "name": "avg_4105_almond_1#2$1"
            }
        },
        {
            "id": 280,
            "prop": "name",
            "attributes": {
                "content": "だけどあの子が必要としてるのは、きっと一つのきっかけにすぎないんだよ。自分自身への認識をはっきりさせるためのね。",
                "name": "ローラ"
            },
            "figure_art": "avg_4105_almond_1#2$1"
        },
        {
            "id": 281,
            "prop": "charslot",
            "attributes": {
                "slot": "m",
                "name": "avg_106_franka_1#3$1"
            }
        },
        {
            "id": 282,
            "prop": "name",
            "attributes": {
                "content": "それで今回がそのきっかけだって？",
                "name": "フランカ"
            },
            "figure_art": "avg_106_franka_1#3$1"
        },
        {
            "id": 283,
            "prop": "charslot",
            "attributes": {
                "slot": "m",
                "name": "avg_4105_almond_1#8$1"
            }
        },
        {
            "id": 284,
            "prop": "name",
            "attributes": {
                "content": "え、いや……そーいうわけでもないんだけど……",
                "name": "ローラ"
            },
            "figure_art": "avg_4105_almond_1#8$1"
        },
        {
            "id": 285,
            "prop": "dialog",
            "attributes": {}
        },
        {
            "id": 286,
            "prop": "Blocker",
            "attributes": {
                "a": 0.0,
                "r": 0.0,
                "g": 0.0,
                "b": 0.0,
                "fadetime": 0.0,
                "block": "true"
            }
        },
        {
            "id": 287,
            "prop": "Blocker",
            "attributes": {
                "a": 1.0,
                "r": 0.0,
                "g": 0.0,
                "b": 0.0,
                "fadetime": 2.0,
                "block": "true"
            }
        },
        {
            "id": 288,
            "prop": "stopmusic",
            "attributes": {
                "fadetime": 2.0
            }
        },
        {
            "id": 289,
            "prop": "charslot",
            "attributes": {}
        },
        {
            "id": 290,
            "prop": "Background",
            "attributes": {
                "image": "bg_iceforest_2",
                "screenadapt": "coverall"
            }
        },
        {
            "id": 291,
            "prop": "Delay",
            "attributes": {
                "time": 1.0
            }
        },
        {
            "id": 292,
            "prop": "Blocker",
            "attributes": {
                "a": 0.0,
                "r": 0.0,
                "g": 0.0,
                "b": 0.0,
                "fadetime": 2.0,
                "block": "true"
            }
        },
        {
            "id": 293,
            "prop": "Delay",
            "attributes": {
                "time": 1.0
            }
        },
        {
            "id": 294,
            "prop": "PlaySound",
            "attributes": {
                "key": "$d_avg_snowbootwalk",
                "volume": 1.0
            }
        },
        {
            "id": 295,
            "prop": "delay",
            "attributes": {
                "time": 1.0
            }
        },
        {
            "id": 296,
            "prop": "PlaySound",
            "attributes": {
                "key": "$d_avg_snowrun",
                "volume": 1.0,
                "loop": "true",
                "channel": "d"
            }
        },
        {
            "id": 297,
            "prop": "charslot",
            "attributes": {
                "slot": "l",
                "name": "avg_npc_1034_1#1$1",
                "posfrom": "300,0",
                "posto": "0,0",
                "duration": 1.5,
                "isblock": "true"
            }
        },
        {
            "id": 298,
            "prop": "StopSound",
            "attributes": {
                "channel": "d",
                "fadetime": 1.0
            }
        },
        {
            "id": 299,
            "prop": "charslot",
            "attributes": {
                "slot": "r",
                "name": "avg_1034_jesca2_1#1$1",
                "posfrom": "200,0",
                "posto": "0,0",
                "duration": 0.8,
                "isblock": "true"
            }
        },
        {
            "id": 300,
            "prop": "charslot",
            "attributes": {
                "slot": "r",
                "name": "avg_1034_jesca2_1#3$1",
                "focus": "r"
            }
        },
        {
            "id": 301,
            "prop": "charslot",
            "attributes": {
                "slot": "l",
                "name": "avg_npc_1034_1#1$1",
                "focus": "n"
            }
        },
        {
            "id": 302,
            "prop": "name",
            "attributes": {
                "content": "あの、お爺さん……お爺さん！",
                "name": "ジェシカ"
            }
        },
        {
            "id": 303,
            "prop": "charslot",
            "attributes": {
                "slot": "l",
                "name": "avg_npc_1034_1#6$1",
                "focus": "l"
            }
        },
        {
            "id": 304,
            "prop": "name",
            "attributes": {
                "content": "なんだ、騒がしいぞ。",
                "name": "年老いた狩人"
            },
            "figure_art": "avg_npc_1034_1#6$1"
        },
        {
            "id": 305,
            "prop": "charslot",
            "attributes": {
                "slot": "r",
                "name": "avg_1034_jesca2_1#9$1",
                "focus": "r"
            }
        },
        {
            "id": 306,
            "prop": "name",
            "attributes": {
                "content": "ごめんなさい、そんなつもりじゃ……あそこを見てもらえますか……",
                "name": "ジェシカ"
            },
            "figure_art": "avg_1034_jesca2_1#9$1"
        },
        {
            "id": 307,
            "prop": "dialog",
            "attributes": {}
        },
        {
            "id": 308,
            "prop": "charslot",
            "attributes": {}
        },
        {
            "id": 309,
            "prop": "name",
            "attributes": {
                "content": "ジェシカは遠くの木のそばにある狩猟罠を指さした。"
            }
        },
        {
            "id": 310,
            "prop": "playMusic",
            "attributes": {
                "key": "$wasteland_loop",
                "volume": 0.6
            }
        },
        {
            "id": 311,
            "prop": "name",
            "attributes": {
                "content": "そこには、前足をがっちりと罠に挟まれた一匹の幼獣がいた。幼獣は苦しげに鳴き続け、挟まれた部分の傷から血がゆっくりとにじみ出ている。"
            }
        },
        {
            "id": 312,
            "prop": "dialog",
            "attributes": {}
        },
        {
            "id": 313,
            "prop": "charslot",
            "attributes": {
                "slot": "m",
                "name": "avg_npc_1034_1#1$1"
            }
        },
        {
            "id": 314,
            "prop": "delay",
            "attributes": {
                "time": 0.5
            }
        },
        {
            "id": 315,
            "prop": "PlaySound",
            "attributes": {
                "key": "$bodyfalldown2",
                "volume": 0.8
            }
        },
        {
            "id": 316,
            "prop": "delay",
            "attributes": {
                "time": 0.5
            }
        },
        {
            "id": 317,
            "prop": "PlaySound",
            "attributes": {
                "key": "$d_avg_snowbootwalk",
                "volume": 1.0
            }
        },
        {
            "id": 318,
            "prop": "charslot",
            "attributes": {
                "duration": 1.5,
                "isblock": "true"
            }
        },
        {
            "id": 319,
            "prop": "name",
            "attributes": {
                "content": "それを見た老狩人は、野獣の死体を下ろして木の下へ向かい、狩猟罠を解いて幼獣をそこから掴み上げた。"
            }
        },
        {
            "id": 320,
            "prop": "charslot",
            "attributes": {
                "slot": "m",
                "name": "avg_1034_jesca2_1#9$1"
            }
        },
        {
            "id": 321,
            "prop": "name",
            "attributes": {
                "content": "まだ子供です……逃がしてあげてもいいかもしれません。もし母親が近くにいたら、すぐに探しに来るでしょうし……",
                "name": "ジェシカ"
            },
            "figure_art": "avg_1034_jesca2_1#9$1"
        },
        {
            "id": 322,
            "prop": "name",
            "attributes": {
                "content": "冬の間は、親子の野獣を見つけても見逃すんですよね？　獣の群れが繁殖できるようにと、そう聞いたことがあります……",
                "name": "ジェシカ"
            },
            "figure_art": "avg_1034_jesca2_1#9$1"
        },
        {
            "id": 323,
            "prop": "charslot",
            "attributes": {
                "slot": "m",
                "name": "avg_npc_1034_1#2$1"
            }
        },
        {
            "id": 324,
            "prop": "name",
            "attributes": {
                "content": "こいつの母親ならもうここにいる。",
                "name": "年老いた狩人"
            },
            "figure_art": "avg_npc_1034_1#2$1"
        },
        {
            "id": 325,
            "prop": "charslot",
            "attributes": {
                "slot": "m",
                "name": "avg_1034_jesca2_1#10$1"
            }
        },
        {
            "id": 326,
            "prop": "name",
            "attributes": {
                "content": "先ほど殺したのがこの子の母親ってことですか？",
                "name": "ジェシカ"
            },
            "figure_art": "avg_1034_jesca2_1#10$1"
        },
        {
            "id": 327,
            "prop": "charslot",
            "attributes": {
                "slot": "m",
                "name": "avg_npc_1034_1#2$1"
            }
        },
        {
            "id": 328,
            "prop": "name",
            "attributes": {
                "content": "そいつが子供を連れてる姿を何度も見かけたことがあるからな。",
                "name": "年老いた狩人"
            },
            "figure_art": "avg_npc_1034_1#2$1"
        },
        {
            "id": 329,
            "prop": "charslot",
            "attributes": {
                "slot": "m",
                "name": "avg_npc_1034_1#1$1"
            }
        },
        {
            "id": 330,
            "prop": "name",
            "attributes": {
                "content": "デカい方が死んで、小さい方もどこぞの馬鹿がしかけた罠にはまっちまったか。ったく、毛皮もダメになった。",
                "name": "年老いた狩人"
            },
            "figure_art": "avg_npc_1034_1#1$1"
        },
        {
            "id": 331,
            "prop": "charslot",
            "attributes": {
                "slot": "m",
                "name": "avg_1034_jesca2_1#9$1"
            }
        },
        {
            "id": 332,
            "prop": "name",
            "attributes": {
                "content": "じゃあ……この幼獣はどうするんですか？",
                "name": "ジェシカ"
            },
            "figure_art": "avg_1034_jesca2_1#9$1"
        },
        {
            "id": 333,
            "prop": "charslot",
            "attributes": {
                "slot": "m",
                "name": "avg_npc_1034_1#1$1"
            }
        },
        {
            "id": 334,
            "prop": "name",
            "attributes": {
                "content": "首を折って、苦しまないように殺してやる。",
                "name": "年老いた狩人"
            },
            "figure_art": "avg_npc_1034_1#1$1"
        },
        {
            "id": 335,
            "prop": "charslot",
            "attributes": {
                "slot": "m",
                "name": "avg_1034_jesca2_1#3$1"
            }
        },
        {
            "id": 336,
            "prop": "name",
            "attributes": {
                "content": "そんな……！",
                "name": "ジェシカ"
            },
            "figure_art": "avg_1034_jesca2_1#3$1"
        },
        {
            "id": 337,
            "prop": "charslot",
            "attributes": {
                "slot": "m",
                "name": "avg_npc_1034_1#1$1"
            }
        },
        {
            "id": 338,
            "prop": "name",
            "attributes": {
                "content": "ならどうしろと？　母親を亡くし、足も折れた。こいつはすぐにでも死ぬ運命だ。",
                "name": "年老いた狩人"
            },
            "figure_art": "avg_npc_1034_1#1$1"
        },
        {
            "id": 339,
            "prop": "charslot",
            "attributes": {
                "slot": "m",
                "name": "avg_npc_1034_1#7$1"
            }
        },
        {
            "id": 340,
            "prop": "name",
            "attributes": {
                "content": "別にここに残してゆっくり息を引き取らせたいというのなら、それでも構わない。俺は何も言わん。",
                "name": "年老いた狩人"
            },
            "figure_art": "avg_npc_1034_1#7$1"
        },
        {
            "id": 341,
            "prop": "charslot",
            "attributes": {
                "slot": "m",
                "name": "avg_1034_jesca2_1#1$1"
            }
        },
        {
            "id": 342,
            "prop": "name",
            "attributes": {
                "content": "……この子はもう生きられない、そうなんですね？",
                "name": "ジェシカ"
            },
            "figure_art": "avg_1034_jesca2_1#1$1"
        },
        {
            "id": 343,
            "prop": "charslot",
            "attributes": {
                "slot": "m",
                "name": "avg_npc_1034_1#7$1"
            }
        },
        {
            "id": 344,
            "prop": "name",
            "attributes": {
                "content": "そうだ。",
                "name": "年老いた狩人"
            },
            "figure_art": "avg_npc_1034_1#7$1"
        },
        {
            "id": 345,
            "prop": "charslot",
            "attributes": {
                "slot": "m",
                "name": "avg_1034_jesca2_1#1$1"
            }
        },
        {
            "id": 346,
            "prop": "name",
            "attributes": {
                "content": "なら、その子をわたしに……",
                "name": "ジェシカ"
            },
            "figure_art": "avg_1034_jesca2_1#1$1"
        },
        {
            "id": 347,
            "prop": "charslot",
            "attributes": {
                "slot": "m",
                "name": "avg_npc_1034_1#1$1"
            }
        },
        {
            "id": 348,
            "prop": "name",
            "attributes": {
                "content": "お前がやるのか？　好きにしろ。",
                "name": "年老いた狩人"
            },
            "figure_art": "avg_npc_1034_1#1$1"
        },
        {
            "id": 349,
            "prop": "dialog",
            "attributes": {}
        },
        {
            "id": 350,
            "prop": "charslot",
            "attributes": {}
        },
        {
            "id": 351,
            "prop": "musicvolume",
            "attributes": {
                "volume": 0.2,
                "fadetime": 2.0
            }
        },
        {
            "id": 352,
            "prop": "charslot",
            "attributes": {
                "slot": "m",
                "name": "avg_1034_jesca2_1#15$1",
                "posfrom": "0,0",
                "posto": "0,-20",
                "afrom": 1.0,
                "ato": 1.0,
                "duration": 2.0,
                "isblock": "true"
            }
        },
        {
            "id": 353,
            "prop": "name",
            "attributes": {
                "content": "よしよし……大丈夫だよ、おチビちゃん……大丈夫だからね。",
                "name": "ジェシカ"
            },
            "figure_art": "avg_1034_jesca2_1#15$1"
        },
        {
            "id": 354,
            "prop": "dialog",
            "attributes": {}
        },
        {
            "id": 355,
            "prop": "charslot",
            "attributes": {
                "duration": 0.5,
                "isblock": "true"
            }
        },
        {
            "id": 356,
            "prop": "name",
            "attributes": {
                "content": "ジェシカは幼獣を腕の中に抱え、毛の流れに沿って優しく撫でた。"
            }
        },
        {
            "id": 357,
            "prop": "name",
            "attributes": {
                "content": "彼女はそれ以上何もせず、幼獣の鳴き声が次第に弱まっていくのをただゆっくりと待ち続けた。それが完全に消えるまで。"
            }
        },
        {
            "id": 358,
            "prop": "dialog",
            "attributes": {}
        },
        {
            "id": 359,
            "prop": "charslot",
            "attributes": {
                "slot": "l",
                "name": "avg_npc_1034_1#1$1"
            }
        },
        {
            "id": 360,
            "prop": "delay",
            "attributes": {
                "time": 1.0
            }
        },
        {
            "id": 361,
            "prop": "musicvolume",
            "attributes": {
                "volume": 0.6,
                "fadetime": 2.0
            }
        },
        {
            "id": 362,
            "prop": "charslot",
            "attributes": {
                "slot": "r",
                "name": "avg_1034_jesca2_1#2$1",
                "posfrom": "0,-20",
                "posto": "0,0",
                "afrom": 0.0,
                "ato": 1.0,
                "duration": 1.5,
                "isblock": "true"
            }
        },
        {
            "id": 363,
            "prop": "charslot",
            "attributes": {
                "slot": "r",
                "name": "avg_1034_jesca2_1#9$1",
                "focus": "r"
            }
        },
        {
            "id": 364,
            "prop": "charslot",
            "attributes": {
                "slot": "l",
                "name": "avg_npc_1034_1#1$1",
                "focus": "n"
            }
        },
        {
            "id": 365,
            "prop": "name",
            "attributes": {
                "content": "この子を救うことはできません。ですが少なくとも……温かい抱擁の中で逝かせてあげることはできます。",
                "name": "ジェシカ"
            }
        },
        {
            "id": 366,
            "prop": "charslot",
            "attributes": {
                "slot": "l",
                "name": "avg_npc_1034_1#2$1",
                "focus": "l"
            }
        },
        {
            "id": 367,
            "prop": "name",
            "attributes": {
                "content": "傭兵がターミナルケアだと？　それも初めて見た。",
                "name": "年老いた狩人"
            },
            "figure_art": "avg_npc_1034_1#2$1"
        },
        {
            "id": 368,
            "prop": "charslot",
            "attributes": {
                "slot": "r",
                "name": "avg_1034_jesca2_1#1$1",
                "focus": "r"
            }
        },
        {
            "id": 369,
            "prop": "name",
            "attributes": {
                "content": "……この子をここに置いていってもいいですか？　獲物なら……大きさで言えばその母親で十分かと思いますが。",
                "name": "ジェシカ"
            },
            "figure_art": "avg_1034_jesca2_1#1$1"
        },
        {
            "id": 370,
            "prop": "charslot",
            "attributes": {
                "slot": "l",
                "name": "avg_npc_1034_1#1$1",
                "focus": "l"
            }
        },
        {
            "id": 371,
            "prop": "name",
            "attributes": {
                "content": "なんだ？　俺にこいつを埋めて、葬式でも挙げてほしいってか？",
                "name": "年老いた狩人"
            },
            "figure_art": "avg_npc_1034_1#1$1"
        },
        {
            "id": 372,
            "prop": "charslot",
            "attributes": {
                "slot": "r",
                "name": "avg_1034_jesca2_1#2$1",
                "focus": "r"
            }
        },
        {
            "id": 373,
            "prop": "name",
            "attributes": {
                "content": "いいえ、冬の林に住む動物は、みんな常にお腹を空かせてるでしょうし、ここに置いていけば……そういった動物たちがお腹を満たせるかもしれないと思って。",
                "name": "ジェシカ"
            },
            "figure_art": "avg_1034_jesca2_1#2$1"
        },
        {
            "id": 374,
            "prop": "charslot",
            "attributes": {
                "slot": "l",
                "name": "avg_npc_1034_1#1$1",
                "focus": "l"
            }
        },
        {
            "id": 375,
            "prop": "name",
            "attributes": {
                "content": "……",
                "name": "年老いた狩人"
            },
            "figure_art": "avg_npc_1034_1#1$1"
        },
        {
            "id": 376,
            "prop": "charslot",
            "attributes": {
                "slot": "r",
                "name": "avg_1034_jesca2_1#1$1",
                "focus": "r"
            }
        },
        {
            "id": 377,
            "prop": "name",
            "attributes": {
                "content": "わたしは確かに情に脆いタイプですが……だからといって、何の分別もつかないわけではありません。",
                "name": "ジェシカ"
            },
            "figure_art": "avg_1034_jesca2_1#1$1"
        },
        {
            "id": 378,
            "prop": "charslot",
            "attributes": {
                "slot": "l",
                "name": "avg_npc_1034_1#10$1",
                "focus": "l"
            }
        },
        {
            "id": 379,
            "prop": "name",
            "attributes": {
                "content": "そうか。ならさっさとついてこい、傭兵の嬢ちゃん。林の中でまた迷子になりたくはないだろ。",
                "name": "年老いた狩人"
            },
            "figure_art": "avg_npc_1034_1#10$1"
        },
        {
            "id": 380,
            "prop": "dialog",
            "attributes": {}
        },
        {
            "id": 381,
            "prop": "Blocker",
            "attributes": {
                "a": 0.0,
                "r": 0.0,
                "g": 0.0,
                "b": 0.0,
                "fadetime": 0.0,
                "block": "true"
            }
        },
        {
            "id": 382,
            "prop": "Blocker",
            "attributes": {
                "a": 1.0,
                "r": 0.0,
                "g": 0.0,
                "b": 0.0,
                "fadetime": 2.0,
                "block": "true"
            }
        },
        {
            "id": 383,
            "prop": "charslot",
            "attributes": {}
        },
        {
            "id": 384,
            "prop": "Background",
            "attributes": {
                "image": "bg_iceforest_2",
                "screenadapt": "coverall"
            }
        },
        {
            "id": 385,
            "prop": "Delay",
            "attributes": {
                "time": 1.0
            }
        },
        {
            "id": 386,
            "prop": "Blocker",
            "attributes": {
                "a": 0.0,
                "r": 0.0,
                "g": 0.0,
                "b": 0.0,
                "fadetime": 2.0,
                "block": "true"
            }
        },
        {
            "id": 387,
            "prop": "PlaySound",
            "attributes": {
                "key": "$d_avg_wind",
                "volume": 1.0
            }
        },
        {
            "id": 388,
            "prop": "Blocker",
            "attributes": {
                "a": 0.0,
                "r": 255.0,
                "g": 255.0,
                "b": 255.0,
                "fadetime": 0.0,
                "block": "true"
            }
        },
        {
            "id": 389,
            "prop": "Blocker",
            "attributes": {
                "a": 0.3,
                "r": 255.0,
                "g": 255.0,
                "b": 255.0,
                "fadetime": 1.0,
                "block": "true"
            }
        },
        {
            "id": 390,
            "prop": "Blocker",
            "attributes": {
                "a": 0.0,
                "r": 255.0,
                "g": 255.0,
                "b": 255.0,
                "fadetime": 3.0,
                "block": "true"
            }
        },
        {
            "id": 391,
            "prop": "PlaySound",
            "attributes": {
                "key": "$d_avg_snowbootwalk",
                "volume": 1.0,
                "loop": "true",
                "channel": "b"
            }
        },
        {
            "id": 392,
            "prop": "StopSound",
            "attributes": {
                "channel": "b",
                "fadetime": 1.5
            }
        },
        {
            "id": 393,
            "prop": "charslot",
            "attributes": {
                "slot": "m",
                "name": "avg_107_liskam_1#1$1",
                "duration": 1.5,
                "isblock": "true"
            }
        },
        {
            "id": 394,
            "prop": "name",
            "attributes": {
                "content": "風のおかげで霧が晴れた……マイルズさん、ここで止まってほしいと言ったのはデイヴィスタウンを眺めたかったからですか？",
                "name": "リスカム"
            },
            "figure_art": "avg_107_liskam_1#1$1"
        },
        {
            "id": 395,
            "prop": "charslot",
            "attributes": {
                "slot": "m",
                "name": "avg_npc_1038_1#8$1"
            }
        },
        {
            "id": 396,
            "prop": "name",
            "attributes": {
                "content": "……若い頃、わしは区画近辺の高い場所から、自分の住んでる町がどんな姿なのか見るのが好きだった。",
                "name": "マイルズ"
            },
            "figure_art": "avg_npc_1038_1#8$1"
        },
        {
            "id": 397,
            "prop": "charslot",
            "attributes": {
                "slot": "m",
                "name": "avg_107_liskam_1#1$1"
            }
        },
        {
            "id": 398,
            "prop": "name",
            "attributes": {
                "content": "当時はどんなふうだったんですか？",
                "name": "リスカム"
            },
            "figure_art": "avg_107_liskam_1#1$1"
        },
        {
            "id": 399,
            "prop": "charslot",
            "attributes": {
                "slot": "m",
                "name": "avg_npc_1038_1#9$1"
            }
        },
        {
            "id": 400,
            "prop": "name",
            "attributes": {
                "content": "賑やかで、輝いてて……もっと活力があった。",
                "name": "マイルズ"
            },
            "figure_art": "avg_npc_1038_1#9$1"
        },
        {
            "id": 401,
            "prop": "charslot",
            "attributes": {
                "slot": "m",
                "name": "avg_107_liskam_1#3$1"
            }
        },
        {
            "id": 402,
            "prop": "name",
            "attributes": {
                "content": "……",
                "name": "リスカム"
            },
            "figure_art": "avg_107_liskam_1#3$1"
        },
        {
            "id": 403,
            "prop": "charslot",
            "attributes": {
                "slot": "m",
                "name": "avg_npc_1038_1#7$1"
            }
        },
        {
            "id": 404,
            "prop": "name",
            "attributes": {
                "content": "今はもう……あぁ、昔には戻れない……もう戻れないんだ。",
                "name": "マイルズ"
            },
            "figure_art": "avg_npc_1038_1#7$1"
        },
        {
            "id": 405,
            "prop": "dialog",
            "attributes": {}
        },
        {
            "id": 406,
            "prop": "PlaySound",
            "attributes": {
                "key": "$d_avg_snowbootwalk",
                "volume": 1.0
            }
        },
        {
            "id": 407,
            "prop": "charslot",
            "attributes": {
                "duration": 2.0,
                "isblock": "true"
            }
        },
        {
            "id": 408,
            "prop": "PlaySound",
            "attributes": {
                "key": "$d_avg_wind",
                "volume": 1.0
            }
        },
        {
            "id": 409,
            "prop": "delay",
            "attributes": {
                "time": 2.0
            }
        },
        {
            "id": 410,
            "prop": "charslot",
            "attributes": {
                "slot": "m",
                "name": "avg_106_franka_1#9$1"
            }
        },
        {
            "id": 411,
            "prop": "name",
            "attributes": {
                "content": "ううっ……ほんと寒い。あたしたちの目的地は……こんな所だったのね。",
                "name": "フランカ"
            },
            "figure_art": "avg_106_franka_1#9$1"
        },
        {
            "id": 412,
            "prop": "charslot",
            "attributes": {
                "slot": "m",
                "name": "avg_4105_almond_1#2$1"
            }
        },
        {
            "id": 413,
            "prop": "name",
            "attributes": {
                "content": "フランカちゃん……",
                "name": "ローラ"
            },
            "figure_art": "avg_4105_almond_1#2$1"
        },
        {
            "id": 414,
            "prop": "charslot",
            "attributes": {
                "slot": "m",
                "name": "avg_106_franka_1#1$1"
            }
        },
        {
            "id": 415,
            "prop": "name",
            "attributes": {
                "content": "なに？",
                "name": "フランカ"
            },
            "figure_art": "avg_106_franka_1#1$1"
        },
        {
            "id": 416,
            "prop": "charslot",
            "attributes": {
                "slot": "m",
                "name": "avg_4105_almond_1#2$1"
            }
        },
        {
            "id": 417,
            "prop": "name",
            "attributes": {
                "content": "いや……ふとジェシカちゃんのことが……",
                "name": "ローラ"
            },
            "figure_art": "avg_4105_almond_1#2$1"
        },
        {
            "id": 418,
            "prop": "charslot",
            "attributes": {
                "slot": "m",
                "name": "avg_106_franka_1#1$1"
            }
        },
        {
            "id": 419,
            "prop": "name",
            "attributes": {
                "content": "なんで？　さっきまで大丈夫だって言ってたじゃない。",
                "name": "フランカ"
            },
            "figure_art": "avg_106_franka_1#1$1"
        },
        {
            "id": 420,
            "prop": "charslot",
            "attributes": {
                "slot": "m",
                "name": "avg_4105_almond_1#3$1"
            }
        },
        {
            "id": 421,
            "prop": "name",
            "attributes": {
                "content": "……さっき話した「きっかけ」について考えてて。",
                "name": "ローラ"
            },
            "figure_art": "avg_4105_almond_1#3$1"
        },
        {
            "id": 422,
            "prop": "charslot",
            "attributes": {
                "slot": "m",
                "name": "avg_106_franka_1#1$1"
            }
        },
        {
            "id": 423,
            "prop": "name",
            "attributes": {
                "content": "ああ、「自分自身への認識をはっきりさせるきっかけ」ってやつ？",
                "name": "フランカ"
            },
            "figure_art": "avg_106_franka_1#1$1"
        },
        {
            "id": 424,
            "prop": "charslot",
            "attributes": {
                "slot": "m",
                "name": "avg_4105_almond_1#3$1"
            }
        },
        {
            "id": 425,
            "prop": "name",
            "attributes": {
                "content": "うん……そのきっかけも、今の風みたいに急にやってくるかもしれないよね。そしたらあまりの冷たさに、ジェシカちゃんも風の中でブルブル震えちゃうかもしれない。",
                "name": "ローラ"
            },
            "figure_art": "avg_4105_almond_1#3$1"
        },
        {
            "id": 426,
            "prop": "charslot",
            "attributes": {
                "slot": "m",
                "name": "avg_4105_almond_1#2$1"
            }
        },
        {
            "id": 427,
            "prop": "name",
            "attributes": {
                "content": "でも、目の前に広がる霧もその風で吹っ飛んじゃうだろう。視界を遮るものがなくなって、すべてがはっきりと目に映るんだ。",
                "name": "ローラ"
            },
            "figure_art": "avg_4105_almond_1#2$1"
        },
        {
            "id": 428,
            "prop": "dialog",
            "attributes": {}
        },
        {
            "id": 429,
            "prop": "charslot",
            "attributes": {}
        },
        {
            "id": 430,
            "prop": "PlaySound",
            "attributes": {
                "key": "$d_avg_snowbootwalk",
                "volume": 1.0,
                "loop": "true",
                "channel": "b"
            }
        },
        {
            "id": 431,
            "prop": "StopSound",
            "attributes": {
                "channel": "b",
                "fadetime": 1.5
            }
        },
        {
            "id": 432,
            "prop": "charslot",
            "attributes": {
                "slot": "m",
                "name": "avg_107_liskam_1#3$1",
                "duration": 1.5
            }
        },
        {
            "id": 433,
            "prop": "delay",
            "attributes": {
                "time": 2.5
            }
        },
        {
            "id": 434,
            "prop": "name",
            "attributes": {
                "content": "その時、彼女の目に映るものが……わたしたちの目前の光景と同じではないことを願ってるよ。",
                "name": "リスカム"
            },
            "figure_art": "avg_107_liskam_1#3$1"
        },
        {
            "id": 435,
            "prop": "dialog",
            "attributes": {}
        },
        {
            "id": 436,
            "prop": "Blocker",
            "attributes": {
                "a": 0.0,
                "r": 0.0,
                "g": 0.0,
                "b": 0.0,
                "fadetime": 0.0,
                "block": "true"
            }
        },
        {
            "id": 437,
            "prop": "Blocker",
            "attributes": {
                "a": 1.0,
                "r": 0.0,
                "g": 0.0,
                "b": 0.0,
                "fadetime": 1.0,
                "block": "true"
            }
        },
        {
            "id": 438,
            "prop": "charslot",
            "attributes": {}
        },
        {
            "id": 439,
            "prop": "delay",
            "attributes": {
                "time": 1.0
            }
        },
        {
            "id": 440,
            "prop": "Image",
            "attributes": {
                "image": "42_i01",
                "xScale": 1.1,
                "yScale": 1.1,
                "x": 0.0,
                "y": 0.0
            }
        },
        {
            "id": 441,
            "prop": "ImageTween",
            "attributes": {
                "image": "42_i01",
                "xScaleFrom": 1.1,
                "yScaleFrom": 1.1,
                "xScaleTo": 1.0,
                "yScaleTo": 1.0,
                "xTo": 0.0,
                "yTo": 0.0,
                "duration": 15.0
            }
        },
        {
            "id": 442,
            "prop": "Blocker",
            "attributes": {
                "a": 0.0,
                "r": 0.0,
                "g": 0.0,
                "b": 0.0,
                "fadetime": 2.0,
                "block": "true"
            }
        },
        {
            "id": 443,
            "prop": "Delay",
            "attributes": {
                "time": 1.0
            }
        },
        {
            "id": 444,
            "prop": "name",
            "attributes": {
                "content": "霧が晴れて現れたのは、折れた木や枝でできた巨大な轍（わだち）が山の斜面に沿ってうねるように、谷の中心まで伸びている光景。"
            }
        },
        {
            "id": 445,
            "prop": "name",
            "attributes": {
                "content": "その果てには、座礁した区画が鎮座している。"
            }
        },
        {
            "id": 446,
            "prop": "name",
            "attributes": {
                "content": "遠く離れてはいたが、区画の中心に高くそびえるエネルギータワーが力なく白い息を吐き出しているのが誰の目にも見て取れた。"
            }
        },
        {
            "id": 447,
            "prop": "name",
            "attributes": {
                "content": "それは、危篤状態の病人のように、苦しそうに息を切らしていた。"
            }
        },
        {
            "id": 448,
            "prop": "dialog",
            "attributes": {}
        },
        {
            "id": 449,
            "prop": "Delay",
            "attributes": {
                "time": 1.0
            }
        },
        {
            "id": 450,
            "prop": "Blocker",
            "attributes": {
                "a": 0.0,
                "r": 0.0,
                "g": 0.0,
                "b": 0.0,
                "fadetime": 0.0,
                "block": "true"
            }
        },
        {
            "id": 451,
            "prop": "Blocker",
            "attributes": {
                "a": 1.0,
                "r": 0.0,
                "g": 0.0,
                "b": 0.0,
                "fadetime": 3.0,
                "block": "true"
            }
        },
        {
            "id": 452,
            "prop": "stopmusic",
            "attributes": {
                "fadetime": 2.0
            }
        },
        {
            "id": 453,
            "prop": "charslot",
            "attributes": {}
        },
        {
            "id": 454,
            "prop": "Background",
            "attributes": {}
        },
        {
            "id": 455,
            "prop": "Image",
            "attributes": {}
        },
        {
            "id": 456,
            "prop": "name",
            "attributes": {
                "content": ""
            }
        }
    ],
    "OPTIONTRACE": true
}