{"lang": "en_US", "eventid": "act48side", "eventName": "Medjehtiqedti Bound", "entryType": "ACTIVITY", "storyCode": "ME-5", "avgTag": "After Operation", "storyName": "Convergence", "storyInfo": "Titi refuses to deceive Minos and decides to steal the fake harp. Kassandra, Lena and Hekádemos try to rescue their friend/patient/rival from prison.\n", "storyList": [{"id": 0, "prop": "HEADER", "attributes": {"key": "title_test", "is_skippable": "true", "fit_mode": "BLACK_MASK"}}, {"id": 1, "prop": "Blocker", "attributes": {"a": 1.0, "r": 0.0, "g": 0.0, "b": 0.0, "fadetime": 0.0, "block": "true"}}, {"id": 2, "prop": "stopmusic", "attributes": {}}, {"id": 3, "prop": "Dialog", "attributes": {}}, {"id": 4, "prop": "Background", "attributes": {"image": "69_g8_templetheater", "screenadapt": "coverall", "block": "true"}}, {"id": 5, "prop": "charslot", "attributes": {"slot": "r", "name": "avg_4056_titi_1#10$2"}}, {"id": 6, "prop": "Delay", "attributes": {"time": 2.0}}, {"id": 7, "prop": "Blocker", "attributes": {"a": 0.0, "r": 0.0, "g": 0.0, "b": 0.0, "fadetime": 2.0, "block": "true"}}, {"id": 8, "prop": "PlayMusic", "attributes": {"intro": "$dignified_intro", "key": "$dignified_loop", "volume": 0.6}}, {"id": 9, "prop": "delay", "attributes": {"time": 1.0}}, {"id": 10, "prop": "PlaySound", "attributes": {"key": "$d_gen_walk_n", "volume": 1.0}}, {"id": 11, "prop": "charslot", "attributes": {"slot": "l", "name": "avgnew_482_pallas_1#10$1", "afrom": 0.0, "ato": 1.0, "duration": 1.5}}, {"id": 12, "prop": "delay", "attributes": {"time": 2.0}}, {"id": 13, "prop": "charslot", "attributes": {"slot": "r", "name": "avg_4056_titi_1#10$2", "focus": "r"}}, {"id": 14, "prop": "charslot", "attributes": {"slot": "l", "name": "avgnew_482_pallas_1#10$1", "focus": "r"}}, {"id": 15, "prop": "name", "attributes": {"content": "......", "name": "Titi"}, "figure_art": "avg_4056_titi_1#10$2"}, {"id": 16, "prop": "charslot", "attributes": {"slot": "l", "name": "avgnew_482_pallas_1#22$1", "focus": "l"}}, {"id": 17, "prop": "name", "attributes": {"content": "Hey, you're the one who invited me. Say something. I skipped the banquet celebrating the completion of the First Temple for you, you know.", "name": "Pallas"}, "figure_art": "avgnew_482_pallas_1#22$1"}, {"id": 18, "prop": "charslot", "attributes": {"slot": "l", "name": "avgnew_482_pallas_1#10$1", "focus": "l"}}, {"id": 19, "prop": "name", "attributes": {"content": "You were a big part of getting the work across the finish line the day before the exchange ceremony. Tradition calls for a full day of celebration. The craftsmen began drinking and reciting poetry in broad daylight.", "name": "Pallas"}, "figure_art": "avgnew_482_pallas_1#10$1"}, {"id": 20, "prop": "charslot", "attributes": {"slot": "r", "name": "avg_4056_titi_1#10$2", "focus": "r"}}, {"id": 21, "prop": "name", "attributes": {"content": "Not all of them hold their drink well. Guess the peace officers will have their hands full tonight.", "name": "Titi"}, "figure_art": "avg_4056_titi_1#10$2"}, {"id": 22, "prop": "charslot", "attributes": {"slot": "l", "name": "avgnew_482_pallas_1#11$1", "focus": "l"}}, {"id": 23, "prop": "name", "attributes": {"content": "Kantia from the moving crew, right? She's really taken to you after you helped her a few times.", "name": "Pallas"}, "figure_art": "avgnew_482_pallas_1#11$1"}, {"id": 24, "prop": "charslot", "attributes": {"slot": "r", "name": "avg_4056_titi_1#1$2", "focus": "r"}}, {"id": 25, "prop": "name", "attributes": {"content": "Yeah... it's been like a dream, coming to Athenius.", "name": "Titi"}, "figure_art": "avg_4056_titi_1#1$2"}, {"id": 26, "prop": "charslot", "attributes": {"slot": "l", "name": "avgnew_482_pallas_1#10$1", "focus": "l"}}, {"id": 27, "prop": "name", "attributes": {"content": "Right you are.", "name": "Pallas"}, "figure_art": "avgnew_482_pallas_1#10$1"}, {"id": 28, "prop": "name", "attributes": {"content": "First day in Athenius, you solved the dispute between the fruit farmers and craftsmen. Then you became the supervisor of the final phase of the temple rebuilding project.", "name": "Pallas"}, "figure_art": "avgnew_482_pallas_1#10$1"}, {"id": 29, "prop": "name", "attributes": {"content": "And you chased Xanthos over multiple blocks after the harp was stolen.", "name": "Pallas"}, "figure_art": "avgnew_482_pallas_1#10$1"}, {"id": 30, "prop": "name", "attributes": {"content": "Way more interesting than just escorting a relic, isn't it?", "name": "Pallas"}, "figure_art": "avgnew_482_pallas_1#10$1"}, {"id": 31, "prop": "charslot", "attributes": {"slot": "r", "name": "avg_4056_titi_1#10$2", "focus": "r"}}, {"id": 32, "prop": "name", "attributes": {"content": "Yeah.", "name": "Titi"}, "figure_art": "avg_4056_titi_1#10$2"}, {"id": 33, "prop": "charslot", "attributes": {"slot": "r", "name": "avg_4056_titi_1#11$2", "focus": "r"}}, {"id": 34, "prop": "name", "attributes": {"content": "But my job was to ensure that the exchange ceremony goes smoothly, and promote the friendship between our two nations.", "name": "Titi"}, "figure_art": "avg_4056_titi_1#11$2"}, {"id": 35, "prop": "charslot", "attributes": {"slot": "l", "name": "avgnew_482_pallas_1#20$1", "focus": "l"}}, {"id": 36, "prop": "name", "attributes": {"content": "What's the matter, Titi? This isn't like you.", "name": "Pallas"}, "figure_art": "avgnew_482_pallas_1#20$1"}, {"id": 37, "prop": "charslot", "attributes": {"slot": "r", "name": "avg_4056_titi_1#2$2", "focus": "r"}}, {"id": 38, "prop": "name", "attributes": {"content": "Pallas...", "name": "Titi"}, "figure_art": "avg_4056_titi_1#2$2"}, {"id": 39, "prop": "charslot", "attributes": {"slot": "r", "name": "avg_4056_titi_1#2$2", "focus": "r"}}, {"id": 40, "prop": "name", "attributes": {"content": "The harp of Kereseira we brought... it's a replica.", "name": "Titi"}, "figure_art": "avg_4056_titi_1#2$2"}, {"id": 41, "prop": "charslot", "attributes": {"slot": "l", "name": "avgnew_482_pallas_1#17$1", "focus": "l"}}, {"id": 42, "prop": "name", "attributes": {"content": "What?", "name": "Pallas"}, "figure_art": "avgnew_482_pallas_1#17$1"}, {"id": 43, "prop": "charslot", "attributes": {"slot": "r", "name": "avg_4056_titi_1#1$2", "focus": "r"}}, {"id": 44, "prop": "name", "attributes": {"content": "I would never have known, if the harp wasn't damaged during my scuffle with Xanthos.", "name": "Titi"}, "figure_art": "avg_4056_titi_1#1$2"}, {"id": 45, "prop": "charslot", "attributes": {"slot": "r", "name": "avg_4056_titi_1#10$2", "focus": "r"}}, {"id": 46, "prop": "name", "attributes": {"content": "Now, my deputy, Behnui, wants to fulfill the padishah's mission by handing over the fake harp in the exchange ceremony... but I know that's not right.", "name": "Titi"}, "figure_art": "avg_4056_titi_1#10$2"}, {"id": 47, "prop": "charslot", "attributes": {"slot": "l", "name": "avgnew_482_pallas_1#8$1", "focus": "l"}}, {"id": 48, "prop": "name", "attributes": {"content": "The ceremony is tomorrow. Do you have a solution?", "name": "Pallas"}, "figure_art": "avgnew_482_pallas_1#8$1"}, {"id": 49, "prop": "charslot", "attributes": {"slot": "r", "name": "avg_4056_titi_1#12$2", "focus": "r"}}, {"id": 50, "prop": "name", "attributes": {"content": "There's no good way to do this. We'd need a miracle.", "name": "Titi"}, "figure_art": "avg_4056_titi_1#12$2"}, {"id": 51, "prop": "charslot", "attributes": {"slot": "r", "name": "avg_4056_titi_1#11$2", "focus": "r"}}, {"id": 52, "prop": "name", "attributes": {"content": "I read through every relevant book I could borrow from the Bibliotheka of Athenius. I learned that the harp of Kereseira was lost to war a long time ago, and it hasn't been seen since.", "name": "Titi"}, "figure_art": "avg_4056_titi_1#11$2"}, {"id": 53, "prop": "name", "attributes": {"content": "It's likely that the Sargonian craftsmen who made this replica had only seen the blueprints, not the harp itself.", "name": "Titi"}, "figure_art": "avg_4056_titi_1#11$2"}, {"id": 54, "prop": "charslot", "attributes": {"slot": "l", "name": "avgnew_482_pallas_1#16$1", "focus": "l"}}, {"id": 55, "prop": "name", "attributes": {"content": "Could the true harp still be in Minos? Or...", "name": "Pallas"}, "figure_art": "avgnew_482_pallas_1#16$1"}, {"id": 56, "prop": "charslot", "attributes": {"slot": "r", "name": "avg_4056_titi_1#12$2", "focus": "r"}}, {"id": 57, "prop": "name", "attributes": {"content": "Or it was destroyed by the fires of war long ago... I'm sorry.", "name": "Titi"}, "figure_art": "avg_4056_titi_1#12$2"}, {"id": 58, "prop": "charslot", "attributes": {"slot": "l", "name": "avgnew_482_pallas_1#16$1", "focus": "l"}}, {"id": 59, "prop": "name", "attributes": {"content": "There's no need for you to apologize.", "name": "Pallas"}, "figure_art": "avgnew_482_pallas_1#16$1"}, {"id": 60, "prop": "charslot", "attributes": {"slot": "l", "name": "avgnew_482_pallas_1#20$1", "focus": "l"}}, {"id": 61, "prop": "name", "attributes": {"content": "What do you plan to do, if the true harp is nowhere to be found?", "name": "Pallas"}, "figure_art": "avgnew_482_pallas_1#20$1"}, {"id": 62, "prop": "charslot", "attributes": {"slot": "r", "name": "avg_4056_titi_1#1$2", "focus": "r"}}, {"id": 63, "prop": "name", "attributes": {"content": "I can't publicly announce in my capacity as Sargonian ambassador that we brought a fake harp. It's more likely to lead to conflict than to reveal the truth.", "name": "Titi"}, "figure_art": "avg_4056_titi_1#1$2"}, {"id": 64, "prop": "charslot", "attributes": {"slot": "l", "name": "avgnew_482_pallas_1#16$1", "focus": "l"}}, {"id": 65, "prop": "name", "attributes": {"content": "A very reasonable concern.", "name": "Pallas"}, "figure_art": "avgnew_482_pallas_1#16$1"}, {"id": 66, "prop": "charslot", "attributes": {"slot": "r", "name": "avg_4056_titi_1#2$2", "focus": "r"}}, {"id": 67, "prop": "name", "attributes": {"content": "And so, I'll have to stop the ceremony in my personal capacity.", "name": "Titi"}, "figure_art": "avg_4056_titi_1#2$2"}, {"id": 68, "prop": "charslot", "attributes": {"slot": "l", "name": "avgnew_482_pallas_1#20$1", "focus": "l"}}, {"id": 69, "prop": "name", "attributes": {"content": "What do you mean?", "name": "Pallas"}, "figure_art": "avgnew_482_pallas_1#20$1"}, {"id": 70, "prop": "charslot", "attributes": {"slot": "r", "name": "avg_4056_titi_1#2$2", "focus": "r"}}, {"id": 71, "prop": "name", "attributes": {"content": "I'm getting rid of the fake harp before the ceremony can start.", "name": "Titi"}, "figure_art": "avg_4056_titi_1#2$2"}, {"id": 72, "prop": "dialog", "attributes": {}}, {"id": 73, "prop": "Blocker", "attributes": {"a": 0.0, "r": 0.0, "g": 0.0, "b": 0.0, "fadetime": 0.0, "block": "true"}}, {"id": 74, "prop": "stopmusic", "attributes": {"fadetime": 2.0}}, {"id": 75, "prop": "Blocker", "attributes": {"a": 1.0, "r": 0.0, "g": 0.0, "b": 0.0, "fadetime": 2.0, "block": "true"}}, {"id": 76, "prop": "charslot", "attributes": {}}, {"id": 77, "prop": "delay", "attributes": {"time": 1.5}}, {"id": 78, "prop": "Background", "attributes": {"image": "69_g4_athenusstreet", "screenadapt": "coverall", "block": "true"}}, {"id": 79, "prop": "Blocker", "attributes": {"a": 0.0, "r": 0.0, "g": 0.0, "b": 0.0, "fadetime": 2.0, "block": "true"}}, {"id": 80, "prop": "delay", "attributes": {"time": 0.5}}, {"id": 81, "prop": "PlayMusic", "attributes": {"intro": "$darkness02_intro", "key": "$darkness02_loop", "volume": 0.6}}, {"id": 82, "prop": "charslot", "attributes": {"slot": "l", "name": "avg_npc_2089_1#1$1", "afrom": 0.0, "ato": 1.0, "duration": 1.5}}, {"id": 83, "prop": "charslot", "attributes": {"slot": "r", "name": "avg_npc_2070_1#8$1", "afrom": 0.0, "ato": 1.0, "duration": 1.5}}, {"id": 84, "prop": "delay", "attributes": {"time": 2.0}}, {"id": 85, "prop": "charslot", "attributes": {"slot": "l", "name": "avg_npc_2089_1#1$1", "focus": "l"}}, {"id": 86, "prop": "charslot", "attributes": {"slot": "r", "name": "avg_npc_2070_1#8$1", "focus": "l"}}, {"id": 87, "prop": "name", "attributes": {"content": "You can't go in.", "name": "Jailer"}, "figure_art": "avg_npc_2089_1#1$1"}, {"id": 88, "prop": "charslot", "attributes": {"slot": "r", "name": "avg_npc_2070_1#10$1", "focus": "r"}}, {"id": 89, "prop": "name", "attributes": {"content": "Look, I know a special visitor's permit is required to visit and deliver supplies. I just forgot.", "name": "Hekádemos"}, "figure_art": "avg_npc_2070_1#10$1"}, {"id": 90, "prop": "name", "attributes": {"content": "Can you accommodate me this once? My old classmate went in a couple of days ago, all of a sudden. His family asked me to bring him some stuff.", "name": "Hekádemos"}, "figure_art": "avg_npc_2070_1#10$1"}, {"id": 91, "prop": "charslot", "attributes": {"slot": "l", "name": "avg_npc_2089_1#1$1", "focus": "l"}}, {"id": 92, "prop": "name", "attributes": {"content": "......", "name": "Jailer"}, "figure_art": "avg_npc_2089_1#1$1"}, {"id": 93, "prop": "charslot", "attributes": {"slot": "r", "name": "avg_npc_2070_1#3$1", "focus": "r"}}, {"id": 94, "prop": "name", "attributes": {"content": "Alright, to tell you the truth, he's pretty sick.", "name": "Hekádemos"}, "figure_art": "avg_npc_2070_1#3$1"}, {"id": 95, "prop": "charslot", "attributes": {"slot": "r", "name": "avg_npc_2070_1#11$1", "focus": "r"}}, {"id": 96, "prop": "name", "attributes": {"content": "The Athenian jail has a doctor and basic medicine, but it's not as effective as the Rhodes Island stuff. He could have an attack while in custody, if he doesn't get proper treatment.", "name": "Hekádemos"}, "figure_art": "avg_npc_2070_1#11$1"}, {"id": 97, "prop": "charslot", "attributes": {"slot": "l", "name": "avg_npc_2089_1#1$1", "focus": "l"}}, {"id": 98, "prop": "name", "attributes": {"content": "Save your breath, it's no use.", "name": "Jailer"}, "figure_art": "avg_npc_2089_1#1$1"}, {"id": 99, "prop": "charslot", "attributes": {"slot": "r", "name": "avg_npc_2070_1#10$1", "focus": "r"}}, {"id": 100, "prop": "name", "attributes": {"content": "Alright. I didn't want to do this...", "name": "Hekádemos"}, "figure_art": "avg_npc_2070_1#10$1"}, {"id": 101, "prop": "charslot", "attributes": {"slot": "r", "name": "avg_npc_2070_1#9$1", "focus": "r"}}, {"id": 102, "prop": "name", "attributes": {"content": "Here's my pass. Hekádemos, Grammateús to the Astynomos.", "name": "Hekádemos"}, "figure_art": "avg_npc_2070_1#9$1"}, {"id": 103, "prop": "name", "attributes": {"content": "I am authorized to enter detention facilities, even bring in suspects for questioning. Open the door. This is an order. I will file the necessary paperwork later.", "name": "Hekádemos"}, "figure_art": "avg_npc_2070_1#9$1"}, {"id": 104, "prop": "charslot", "attributes": {"slot": "l", "name": "avg_npc_2089_1#1$1", "focus": "l"}}, {"id": 105, "prop": "name", "attributes": {"content": "......", "name": "Jailer"}, "figure_art": "avg_npc_2089_1#1$1"}, {"id": 106, "prop": "name", "attributes": {"content": "You want to see the two thieves who came in a few days ago?", "name": "Jailer"}, "figure_art": "avg_npc_2089_1#1$1"}, {"id": 107, "prop": "charslot", "attributes": {"slot": "r", "name": "avg_npc_2070_1#9$1", "focus": "r"}}, {"id": 108, "prop": "multiline", "attributes": {"name": "Hekádemos", "content": "Lykeion is not a... "}}, {"id": 109, "prop": "charslot", "attributes": {"slot": "r", "name": "avg_npc_2070_1#8$1", "focus": "r"}}, {"id": 110, "prop": "multiline", "attributes": {"name": "Hekádemos", "content": "Never mind. Yes."}}, {"id": 111, "prop": "charslot", "attributes": {"slot": "l", "name": "avg_npc_2089_1#1$1", "focus": "l"}}, {"id": 112, "prop": "name", "attributes": {"content": "You can't.", "name": "Jailer"}, "figure_art": "avg_npc_2089_1#1$1"}, {"id": 113, "prop": "charslot", "attributes": {"slot": "r", "name": "avg_npc_2070_1#5$1", "focus": "r"}}, {"id": 114, "prop": "name", "attributes": {"content": "What? Why not?!", "name": "Hekádemos"}, "figure_art": "avg_npc_2070_1#5$1"}, {"id": 115, "prop": "charslot", "attributes": {"slot": "l", "name": "avg_npc_2089_1#1$1", "focus": "l"}}, {"id": 116, "prop": "name", "attributes": {"content": "You are authorized to see prisoners held at the jail, but the two you're looking for aren't here anymore.", "name": "Jailer"}, "figure_art": "avg_npc_2089_1#1$1"}, {"id": 117, "prop": "charslot", "attributes": {"slot": "r", "name": "avg_npc_2070_1#4$1", "focus": "r"}}, {"id": 118, "prop": "multiline", "attributes": {"name": "Hekádemos", "content": "Were they transferred? "}}, {"id": 119, "prop": "charslot", "attributes": {"slot": "r", "name": "avg_npc_2070_1#3$1", "focus": "r"}}, {"id": 120, "prop": "multiline", "attributes": {"name": "Hekádemos", "content": "That is unusual. Has Kyría Athopoulou's Oripathy treatment system been implemented already?"}}, {"id": 121, "prop": "charslot", "attributes": {"slot": "r", "name": "avg_npc_2070_1#9$1", "focus": "r"}}, {"id": 122, "prop": "name", "attributes": {"content": "Where were they transferred?", "name": "Hekádemos"}, "figure_art": "avg_npc_2070_1#9$1"}, {"id": 123, "prop": "charslot", "attributes": {"slot": "l", "name": "avg_npc_2089_1#1$1", "focus": "l"}}, {"id": 124, "prop": "name", "attributes": {"content": "Don't bother, Hekádemos. I don't know who they are to you, but not even the Grammateús to the Astynomos is authorized to see inmates on death row.", "name": "Jailer"}, "figure_art": "avg_npc_2089_1#1$1"}, {"id": 125, "prop": "CameraShake", "attributes": {"duration": 0.2, "xstrength": 30.0, "ystrength": 30.0, "vibrato": 30.0, "randomness": 90.0, "fadeout": "true", "block": "false"}}, {"id": 126, "prop": "charslot", "attributes": {"slot": "r", "name": "avg_npc_2070_1#4$1", "focus": "r"}}, {"id": 127, "prop": "name", "attributes": {"content": "Death row?!", "name": "Hekádemos"}, "figure_art": "avg_npc_2070_1#4$1"}, {"id": 128, "prop": "dialog", "attributes": {}}, {"id": 129, "prop": "Blocker", "attributes": {"a": 0.0, "r": 0.0, "g": 0.0, "b": 0.0, "fadetime": 0.0, "block": "true"}}, {"id": 130, "prop": "Blocker", "attributes": {"a": 1.0, "r": 0.0, "g": 0.0, "b": 0.0, "fadetime": 2.0, "block": "true"}}, {"id": 131, "prop": "charslot", "attributes": {}}, {"id": 132, "prop": "delay", "attributes": {"time": 1.0}}, {"id": 133, "prop": "Background", "attributes": {"image": "69_g10_templegarden", "screenadapt": "coverall", "block": "true"}}, {"id": 134, "prop": "charslot", "attributes": {"slot": "l", "name": "avg_1022_flwr2_1#4$2"}}, {"id": 135, "prop": "Blocker", "attributes": {"a": 0.0, "r": 0.0, "g": 0.0, "b": 0.0, "fadetime": 2.0, "block": "true"}}, {"id": 136, "prop": "delay", "attributes": {"time": 0.5}}, {"id": 137, "prop": "PlaySound", "attributes": {"key": "$d_gen_walk_n", "volume": 0.6, "channel": "1"}}, {"id": 138, "prop": "StopSound", "attributes": {"channel": "1", "fadetime": 1.5}}, {"id": 139, "prop": "charslot", "attributes": {"slot": "r", "name": "avg_npc_2075_1#1$1", "afrom": 0.0, "ato": 1.0, "duration": 1.5}}, {"id": 140, "prop": "delay", "attributes": {"time": 2.0}}, {"id": 141, "prop": "charslot", "attributes": {"slot": "l", "name": "avg_1022_flwr2_1#4$2", "focus": "r"}}, {"id": 142, "prop": "charslot", "attributes": {"slot": "r", "name": "avg_npc_2075_1#1$1", "focus": "r"}}, {"id": 143, "prop": "name", "attributes": {"content": "Sorry, Kyría Athopoulou...", "name": "Clerk"}, "figure_art": "avg_npc_2075_1#1$1"}, {"id": 144, "prop": "charslot", "attributes": {"slot": "l", "name": "avg_1022_flwr2_1#18$2", "focus": "l"}}, {"id": 145, "prop": "name", "attributes": {"content": "Does Lydia... I mean, does the Astynomos really not have the time?", "name": "Lena"}, "figure_art": "avg_1022_flwr2_1#18$2"}, {"id": 146, "prop": "charslot", "attributes": {"slot": "l", "name": "avg_1022_flwr2_1#16$2", "focus": "l"}}, {"id": 147, "prop": "name", "attributes": {"content": "I heard that Xanthos and his apprentice were arrested for theft.", "name": "Lena"}, "figure_art": "avg_1022_flwr2_1#16$2"}, {"id": 148, "prop": "name", "attributes": {"content": "They're my patients, and in a key stage of treatment, as the Rhodes Island clinic already reported.", "name": "Lena"}, "figure_art": "avg_1022_flwr2_1#16$2"}, {"id": 149, "prop": "charslot", "attributes": {"slot": "l", "name": "avg_1022_flwr2_1#18$2", "focus": "l"}}, {"id": 150, "prop": "name", "attributes": {"content": "Xanthos's Blood Originium-Crystal Density is particularly high, which could potentially lead to an acute attack of Oripathy. I would like to deliver medicine to them...", "name": "Lena"}, "figure_art": "avg_1022_flwr2_1#18$2"}, {"id": 151, "prop": "charslot", "attributes": {"slot": "r", "name": "avg_npc_2075_1#1$1", "focus": "r"}}, {"id": 152, "prop": "name", "attributes": {"content": "Look, I don't understand any of the medical jargon you're throwing around.", "name": "Clerk"}, "figure_art": "avg_npc_2075_1#1$1"}, {"id": 153, "prop": "name", "attributes": {"content": "We are all very grateful to you for returning to Athenius, bringing back medical knowledge that you learned abroad and establishing an Oripathy clinic, but...", "name": "Clerk"}, "figure_art": "avg_npc_2075_1#1$1"}, {"id": 154, "prop": "name", "attributes": {"content": "I shouldn't talk too much, but you're a good doctor, and the Astynomos' sister. You really should keep your distance from her for a few days at least, if only for the sake of your relationship.", "name": "Clerk"}, "figure_art": "avg_npc_2075_1#1$1"}, {"id": 155, "prop": "charslot", "attributes": {"slot": "l", "name": "avg_1022_flwr2_1#16$2", "focus": "l"}}, {"id": 156, "prop": "name", "attributes": {"content": "Why?", "name": "Lena"}, "figure_art": "avg_1022_flwr2_1#16$2"}, {"id": 157, "prop": "charslot", "attributes": {"slot": "r", "name": "avg_npc_2075_1#1$1", "focus": "r"}}, {"id": 158, "prop": "name", "attributes": {"content": "The official line says the crime was theft, but the Sargonian ambassador came here a few days ago and said the thing that was stolen wasn't the ambassador's personal item, but an important relic for the exchange ceremony.", "name": "Clerk"}, "figure_art": "avg_npc_2075_1#1$1"}, {"id": 159, "prop": "name", "attributes": {"content": "He put a lot of pressure on Lydia. They're probably going to be publicly charged with treason, once the ceremony is over.", "name": "Clerk"}, "figure_art": "avg_npc_2075_1#1$1"}, {"id": 160, "prop": "charslot", "attributes": {"slot": "l", "name": "avg_1022_flwr2_1#11$2", "focus": "l"}}, {"id": 161, "prop": "name", "attributes": {"content": "Treason?! But according to Minoan law—", "name": "Lena"}, "figure_art": "avg_1022_flwr2_1#11$2"}, {"id": 162, "prop": "charslot", "attributes": {"slot": "r", "name": "avg_npc_2075_1#1$1", "focus": "r"}}, {"id": 163, "prop": "name", "attributes": {"content": "Most of the issues the Astynomos faces cannot be solved through legal procedures.", "name": "Clerk"}, "figure_art": "avg_npc_2075_1#1$1"}, {"id": 164, "prop": "name", "attributes": {"content": "She wants a new, modern Minos, and she is willing to give everything for it. That's why we're willing to work for her.", "name": "Clerk"}, "figure_art": "avg_npc_2075_1#1$1"}, {"id": 165, "prop": "name", "attributes": {"content": "Perhaps you're not aware, but she gave up her family inheritance, even chasing her other family out of Athenius after taking office...", "name": "Clerk"}, "figure_art": "avg_npc_2075_1#1$1"}, {"id": 166, "prop": "charslot", "attributes": {"slot": "l", "name": "avg_1022_flwr2_1#11$2", "focus": "l"}}, {"id": 167, "prop": "multiline", "attributes": {"name": "Lena", "content": "She gave up her inheritance? "}}, {"id": 168, "prop": "charslot", "attributes": {"slot": "l", "name": "avg_1022_flwr2_1#18$2", "focus": "l"}}, {"id": 169, "prop": "multiline", "attributes": {"name": "Lena", "content": "I thought the business failed..."}}, {"id": 170, "prop": "charslot", "attributes": {"slot": "r", "name": "avg_npc_2075_1#1$1", "focus": "r"}}, {"id": 171, "prop": "name", "attributes": {"content": "This exchange of relics is an important part of her administration. There must be no mistake, at least not on the surface... even if it means sacrificing two lives. It's not like they're innocent, after all.", "name": "Clerk"}, "figure_art": "avg_npc_2075_1#1$1"}, {"id": 172, "prop": "charslot", "attributes": {"slot": "l", "name": "avg_1022_flwr2_1#9$2", "focus": "l"}}, {"id": 173, "prop": "name", "attributes": {"content": "......", "name": "Lena"}, "figure_art": "avg_1022_flwr2_1#9$2"}, {"id": 174, "prop": "charslot", "attributes": {"slot": "r", "name": "avg_npc_2075_1#1$1", "focus": "r"}}, {"id": 175, "prop": "name", "attributes": {"content": "I'm sorry... I have to get back to work.", "name": "Clerk"}, "figure_art": "avg_npc_2075_1#1$1"}, {"id": 176, "prop": "dialog", "attributes": {}}, {"id": 177, "prop": "PlaySound", "attributes": {"key": "$d_gen_walk_n", "volume": 0.6, "channel": "2"}}, {"id": 178, "prop": "StopSound", "attributes": {"channel": "2", "fadetime": 2.0}}, {"id": 179, "prop": "charslot", "attributes": {"slot": "r", "afrom": 1.0, "ato": 0.0, "posfrom": "0,0", "posto": "150,0", "duration": 1.5, "focus": "r"}}, {"id": 180, "prop": "delay", "attributes": {"time": 2.5}}, {"id": 181, "prop": "charslot", "attributes": {"slot": "l", "name": "avg_1022_flwr2_1#9$2", "focus": "l"}}, {"id": 182, "prop": "multiline", "attributes": {"name": "Lena", "content": "What is Lydia...? "}}, {"id": 183, "prop": "charslot", "attributes": {"slot": "l", "name": "avg_1022_flwr2_1#18$2", "focus": "l"}}, {"id": 184, "prop": "multiline", "attributes": {"name": "Lena", "content": "Well, she wouldn't meet with me, and I doubt I can convince her, even if we did meet."}}, {"id": 185, "prop": "charslot", "attributes": {"slot": "l", "name": "avg_1022_flwr2_1#4$2", "focus": "l"}}, {"id": 186, "prop": "name", "attributes": {"content": "But Xanthos and Lykeion need to be tried fairly. I can't let Lydia make a mistake like this. What do I do?", "name": "Lena"}, "figure_art": "avg_1022_flwr2_1#4$2"}, {"id": 187, "prop": "dialog", "attributes": {}}, {"id": 188, "prop": "charslot", "attributes": {"slot": "l", "name": "avg_1022_flwr2_1#4$2"}}, {"id": 189, "prop": "charslot", "attributes": {"slot": "r", "name": "avg_npc_2070_1#11$1", "bstart": 0.1, "bend": 0.3, "posfrom": "0,0", "posto": "200,0", "duration": 0.0}}, {"id": 190, "prop": "PlaySound", "attributes": {"key": "$rungeneral", "volume": 1.0, "channel": "3"}}, {"id": 191, "prop": "StopSound", "attributes": {"channel": "3", "fadetime": 1.5}}, {"id": 192, "prop": "charslot", "attributes": {"slot": "r", "posfrom": "200,0", "posto": "-130,0", "duration": 1.0}}, {"id": 193, "prop": "delay", "attributes": {"time": 1.0}}, {"id": 194, "prop": "PlaySound", "attributes": {"key": "$d_avg_punchsp3", "volume": 1.0}}, {"id": 195, "prop": "CameraShake", "attributes": {"duration": 0.5, "xstrength": 30.0, "ystrength": 30.0, "vibrato": 50.0, "randomness": 80.0, "fadeout": "true", "block": "false"}}, {"id": 196, "prop": "charslot", "attributes": {"slot": "l", "name": "avg_1022_flwr2_1#11$2"}}, {"id": 197, "prop": "charslot", "attributes": {"slot": "l", "posfrom": "0,0", "posto": "-120,0", "duration": 0.5}}, {"id": 198, "prop": "charslot", "attributes": {"slot": "r", "posfrom": "-130,0", "posto": "-10,0", "duration": 0.5}}, {"id": 199, "prop": "delay", "attributes": {"time": 0.7}}, {"id": 200, "prop": "charslot", "attributes": {"slot": "r", "name": "avg_npc_2070_1#4$1", "bstart": 0.1, "bend": 0.3, "focus": "r"}}, {"id": 201, "prop": "name", "attributes": {"content": "Sorry, I was lost in thought—", "name": "???"}, "figure_art": "avg_npc_2070_1#4$1"}, {"id": 202, "prop": "dialog", "attributes": {}}, {"id": 203, "prop": "delay", "attributes": {"time": 1.0}}, {"id": 204, "prop": "charslot", "attributes": {"slot": "m", "name": "avg_npc_2070_1#4$1", "posfrom": "0,0", "posto": "190,0", "duration": 0.0}}, {"id": 205, "prop": "charslot", "attributes": {"slot": "l", "name": "avg_1022_flwr2_1#11$2", "focus": "r"}}, {"id": 206, "prop": "charslot", "attributes": {"slot": "r", "afrom": 1.0, "ato": 0.0, "duration": 1.5, "focus": "r"}}, {"id": 207, "prop": "delay", "attributes": {"time": 1.5}}, {"id": 208, "prop": "charslot", "attributes": {"slot": "m", "name": "avg_npc_2070_1#4$1", "focus": "m"}}, {"id": 209, "prop": "name", "attributes": {"content": "Kyría Athopoulou?", "name": "Hekádemos"}, "figure_art": "avg_npc_2070_1#4$1"}, {"id": 210, "prop": "dialog", "attributes": {}}, {"id": 211, "prop": "Blocker", "attributes": {"a": 0.0, "r": 0.0, "g": 0.0, "b": 0.0, "fadetime": 0.0, "block": "true"}}, {"id": 212, "prop": "stopmusic", "attributes": {"fadetime": 2.0}}, {"id": 213, "prop": "Blocker", "attributes": {"a": 1.0, "r": 0.0, "g": 0.0, "b": 0.0, "fadetime": 2.0, "block": "true"}}, {"id": 214, "prop": "delay", "attributes": {"time": 0.5}}, {"id": 215, "prop": "charslot", "attributes": {}}, {"id": 216, "prop": "delay", "attributes": {"time": 1.5}}, {"id": 217, "prop": "Background", "attributes": {"image": "69_g14_luxuriousroom", "screenadapt": "coverall", "block": "true"}}, {"id": 218, "prop": "charslot", "attributes": {"slot": "l", "name": "avg_npc_2068_1#1$1", "posfrom": "0,0", "posto": "-50,0", "duration": 0.0}}, {"id": 219, "prop": "charslot", "attributes": {"slot": "r", "name": "avg_npc_2067_1#1$1", "posfrom": "0,0", "posto": "50,0", "duration": 0.0}}, {"id": 220, "prop": "Blocker", "attributes": {"a": 0.0, "r": 0.0, "g": 0.0, "b": 0.0, "fadetime": 2.0, "block": "true"}}, {"id": 221, "prop": "delay", "attributes": {"time": 0.5}}, {"id": 222, "prop": "PlayMusic", "attributes": {"intro": "$plot_intro", "key": "$plot_loop", "volume": 0.6}}, {"id": 223, "prop": "charslot", "attributes": {"slot": "l", "name": "avg_npc_2068_1#1$1", "focus": "l"}}, {"id": 224, "prop": "charslot", "attributes": {"slot": "r", "name": "avg_npc_2067_1#1$1", "focus": "l"}}, {"id": 225, "prop": "name", "attributes": {"content": "You've been staring out the window, Astynomos.", "name": "Kassandra"}, "figure_art": "avg_npc_2068_1#1$1"}, {"id": 226, "prop": "charslot", "attributes": {"slot": "r", "name": "avg_npc_2067_1#7$1", "focus": "r"}}, {"id": 227, "prop": "name", "attributes": {"content": "Apologies, Hiéreia Kassandra.", "name": "Lydia"}, "figure_art": "avg_npc_2067_1#7$1"}, {"id": 228, "prop": "charslot", "attributes": {"slot": "l", "name": "avg_npc_2068_1#1$1", "focus": "l"}}, {"id": 229, "prop": "name", "attributes": {"content": "Why not let Kyría Athopoulou in? I have to discuss the establishment of an Oripathy treatment system with her anyway.", "name": "Kassandra"}, "figure_art": "avg_npc_2068_1#1$1"}, {"id": 230, "prop": "charslot", "attributes": {"slot": "r", "name": "avg_npc_2067_1#1$1", "focus": "r"}}, {"id": 231, "prop": "name", "attributes": {"content": "Oh? I thought you wanted to get extra help to plead the case of the two Infected who were arrested a few days ago.", "name": "Lydia"}, "figure_art": "avg_npc_2067_1#1$1"}, {"id": 232, "prop": "name", "attributes": {"content": "You know that ferryman, Xanthos, quite well. I believe you were the one who found him the job at the crossing?", "name": "Lydia"}, "figure_art": "avg_npc_2067_1#1$1"}, {"id": 233, "prop": "charslot", "attributes": {"slot": "l", "name": "avg_npc_2068_1#1$1", "focus": "l"}}, {"id": 234, "prop": "name", "attributes": {"content": "The peace officers will deal with this theft. Neither of us need to worry about it.", "name": "Kassandra"}, "figure_art": "avg_npc_2068_1#1$1"}, {"id": 235, "prop": "charslot", "attributes": {"slot": "r", "name": "avg_npc_2067_1#8$1", "focus": "r"}}, {"id": 236, "prop": "name", "attributes": {"content": "I'm afraid I don't have that luxury. If this incident affects the trust between us and Sargon, then this incident will become more than a simple theft...", "name": "Lydia"}, "figure_art": "avg_npc_2067_1#8$1"}, {"id": 237, "prop": "charslot", "attributes": {"slot": "l", "name": "avg_npc_2068_1#5$1", "focus": "l"}}, {"id": 238, "prop": "name", "attributes": {"content": "What?", "name": "Kassandra"}, "figure_art": "avg_npc_2068_1#5$1"}, {"id": 239, "prop": "charslot", "attributes": {"slot": "r", "name": "avg_npc_2067_1#1$1", "focus": "r"}}, {"id": 240, "prop": "name", "attributes": {"content": "It's my own business. It has nothing to do with a priestess of Endymion Temple.", "name": "Lydia"}, "figure_art": "avg_npc_2067_1#1$1"}, {"id": 241, "prop": "charslot", "attributes": {"slot": "r", "name": "avg_npc_2067_1#2$1", "focus": "r"}}, {"id": 242, "prop": "name", "attributes": {"content": "Back on topic, Hiéreia Kassandra. The opening play for tomorrow's exchange ceremony has been decided. It is to be <i>King Pertheus</i>, a popular classic across Terra.", "name": "Lydia"}, "figure_art": "avg_npc_2067_1#2$1"}, {"id": 243, "prop": "name", "attributes": {"content": "All the priests need to do is attend. There will be no need for complicated rituals.", "name": "Lydia"}, "figure_art": "avg_npc_2067_1#2$1"}, {"id": 244, "prop": "charslot", "attributes": {"slot": "l", "name": "avg_npc_2068_1#4$1", "focus": "l"}}, {"id": 245, "prop": "name", "attributes": {"content": "......", "name": "Kassandra"}, "figure_art": "avg_npc_2068_1#4$1"}, {"id": 246, "prop": "charslot", "attributes": {"slot": "l", "name": "avg_npc_2068_1#1$1", "focus": "l"}}, {"id": 247, "prop": "name", "attributes": {"content": "A few weeks ago, I came to discuss the priest-directed ceremonial play for the completion of Kereseira's First Temple. I have not seen you at the Astynomos' Office since.", "name": "Kassandra"}, "figure_art": "avg_npc_2068_1#1$1"}, {"id": 248, "prop": "charslot", "attributes": {"slot": "r", "name": "avg_npc_2067_1#1$1", "focus": "r"}}, {"id": 249, "prop": "name", "attributes": {"content": "I apologize. My schedule is a busy one. I certainly remember. The exchange ceremony also requires an opening play, and we can kill two fowlbeasts with one stone this way. We need not bother the priests, however.", "name": "Lydia"}, "figure_art": "avg_npc_2067_1#1$1"}, {"id": 250, "prop": "charslot", "attributes": {"slot": "l", "name": "avg_npc_2068_1#8$1", "focus": "l"}}, {"id": 251, "prop": "name", "attributes": {"content": "Excuse me, but the rebuilding of Kereseira's First Temple is a symbol of the people's spirit. Now that it is complete, tradition calls for a proper ceremony to invite the heroes to enter the temple and give Minos their blessings.", "name": "Kassandra"}, "figure_art": "avg_npc_2068_1#8$1"}, {"id": 252, "prop": "name", "attributes": {"content": "The council is not trying to usurp your administrative power, and the exchange ceremony does fall within your responsibility.", "name": "Kassandra"}, "figure_art": "avg_npc_2068_1#8$1"}, {"id": 253, "prop": "charslot", "attributes": {"slot": "l", "name": "avg_npc_2068_1#10$1", "focus": "l"}}, {"id": 254, "prop": "name", "attributes": {"content": "However, Minoan drama began as a ritualistic performance.", "name": "Kassandra"}, "figure_art": "avg_npc_2068_1#10$1"}, {"id": 255, "prop": "name", "attributes": {"content": "Every single detail is carefully arranged, from the props to the program to the performers. It's not enough to simply put on a popular play.", "name": "Kassandra"}, "figure_art": "avg_npc_2068_1#10$1"}, {"id": 256, "prop": "charslot", "attributes": {"slot": "r", "name": "avg_npc_2067_1#7$1", "focus": "r"}}, {"id": 257, "prop": "name", "attributes": {"content": "'Immortal legend'... 'witness of the oracle'... 'heroic relic'...", "name": "Lydia"}, "figure_art": "avg_npc_2067_1#7$1"}, {"id": 258, "prop": "charslot", "attributes": {"slot": "r", "name": "avg_npc_2067_1#8$1", "focus": "r"}}, {"id": 259, "prop": "name", "attributes": {"content": "Do not think that I am completely ignorant of traditional ceremony, or that I'm one of those radicals who calls for every tradition to be abolished.", "name": "Lydia"}, "figure_art": "avg_npc_2067_1#8$1"}, {"id": 260, "prop": "name", "attributes": {"content": "But even if you have your choice of the program and control over the troupe, there is still something missing from the traditional ritual that you want, isn't there?", "name": "Lydia"}, "figure_art": "avg_npc_2067_1#8$1"}, {"id": 261, "prop": "charslot", "attributes": {"slot": "l", "name": "avg_npc_2068_1#4$1", "focus": "l"}}, {"id": 262, "prop": "name", "attributes": {"content": "...The Sargonian mission brought Kereseira's harp.", "name": "Kassandra"}, "figure_art": "avg_npc_2068_1#4$1"}, {"id": 263, "prop": "charslot", "attributes": {"slot": "r", "name": "avg_npc_2067_1#4$1", "focus": "r"}}, {"id": 264, "prop": "name", "attributes": {"content": "Oh? You <i>do</i> recognize the relic's ritual significance?", "name": "Lydia"}, "figure_art": "avg_npc_2067_1#4$1"}, {"id": 265, "prop": "charslot", "attributes": {"slot": "l", "name": "avg_npc_2068_1#8$1", "focus": "l"}}, {"id": 266, "prop": "name", "attributes": {"content": "...What do you mean?", "name": "Kassandra"}, "figure_art": "avg_npc_2068_1#8$1"}, {"id": 267, "prop": "charslot", "attributes": {"slot": "r", "name": "avg_npc_2067_1#1$1", "focus": "r"}}, {"id": 268, "prop": "name", "attributes": {"content": "I'm neither an archaeologist nor a historian. As Astynomos, however, I understand every priest who sits on the council, including you.", "name": "Lydia"}, "figure_art": "avg_npc_2067_1#1$1"}, {"id": 269, "prop": "name", "attributes": {"content": "You are the head priestess of Endymion Temple, and endowed with the divine gift of speaking on behalf of the heroes. Your knowledge of heroic epics puts most scholars to shame.", "name": "Lydia"}, "figure_art": "avg_npc_2067_1#1$1"}, {"id": 270, "prop": "charslot", "attributes": {"slot": "r", "name": "avg_npc_2067_1#7$1", "focus": "r"}}, {"id": 271, "prop": "name", "attributes": {"content": "Yet you showed no interest about the harp of Kereseira that the Sargonian mission brought with them. You didn't even ask to see it.", "name": "Lydia"}, "figure_art": "avg_npc_2067_1#7$1"}, {"id": 272, "prop": "charslot", "attributes": {"slot": "r", "name": "avg_npc_2067_1#1$1", "focus": "r"}}, {"id": 273, "prop": "name", "attributes": {"content": "I don't know why exactly, but I can tell that the harp the Sargonian mission brought was not the heroic relic that you knew.", "name": "Lydia"}, "figure_art": "avg_npc_2067_1#1$1"}, {"id": 274, "prop": "name", "attributes": {"content": "The ceremonial play could not have been performed to begin with.", "name": "Lydia"}, "figure_art": "avg_npc_2067_1#1$1"}, {"id": 275, "prop": "charslot", "attributes": {"slot": "l", "name": "avg_npc_2068_1#6$1", "focus": "l"}}, {"id": 276, "prop": "name", "attributes": {"content": "No, I already...", "name": "Kassandra"}, "figure_art": "avg_npc_2068_1#6$1"}, {"id": 277, "prop": "charslot", "attributes": {"slot": "r", "name": "avg_npc_2067_1#1$1", "focus": "r"}}, {"id": 278, "prop": "name", "attributes": {"content": "I have nothing against the council, Hiéreia Kassandra. If you present a legitimate heroic relic for the ceremony, I would be more than happy to give the choice of play back to you.", "name": "Lydia"}, "figure_art": "avg_npc_2067_1#1$1"}, {"id": 279, "prop": "charslot", "attributes": {"slot": "r", "name": "avg_npc_2067_1#7$1", "focus": "r"}}, {"id": 280, "prop": "name", "attributes": {"content": "For the past century, however, the temples have mostly used crude replicas in place of true relics for your ceremonies. I don't need to tell you that the link between us and the heroes is weakening.", "name": "Lydia"}, "figure_art": "avg_npc_2067_1#7$1"}, {"id": 281, "prop": "charslot", "attributes": {"slot": "r", "name": "avg_npc_2067_1#1$1", "focus": "r"}}, {"id": 282, "prop": "name", "attributes": {"content": "As a modern state, Minos can no longer rely on ancient legends to unite our people's spirit. No need to worry, however. The temples and priests will continue to exist.", "name": "Lydia"}, "figure_art": "avg_npc_2067_1#1$1"}, {"id": 283, "prop": "charslot", "attributes": {"slot": "r", "name": "avg_npc_2067_1#2$1", "focus": "r"}}, {"id": 284, "prop": "name", "attributes": {"content": "You can continue to contribute to historical research and tourism.", "name": "Lydia"}, "figure_art": "avg_npc_2067_1#2$1"}, {"id": 285, "prop": "charslot", "attributes": {"slot": "l", "name": "avg_npc_2068_1#4$1", "focus": "l"}}, {"id": 286, "prop": "name", "attributes": {"content": "......", "name": "Kassandra"}, "figure_art": "avg_npc_2068_1#4$1"}, {"id": 287, "prop": "Dialog", "attributes": {}}, {"id": 288, "prop": "Delay", "attributes": {"time": 1.0}}, {"id": 289, "prop": "Blocker", "attributes": {"a": 1.0, "r": 0.0, "g": 0.0, "b": 0.0, "fadetime": 2.0, "block": "true"}}, {"id": 290, "prop": "stopmusic", "attributes": {"fadetime": 2.0}}, {"id": 291, "prop": "Image", "attributes": {}}, {"id": 292, "prop": "charslot", "attributes": {}}, {"id": 293, "prop": "name", "attributes": {"content": ""}}], "OPTIONTRACE": true}